{"traffic_history": [{"timestamp": "2026-04-27T04:09:37.634230", "incoming": 1390, "outgoing": 226}, {"timestamp": "2026-04-27T04:09:38.698394", "incoming": 459, "outgoing": 73}, {"timestamp": "2026-04-27T04:09:39.836580", "incoming": 1272, "outgoing": 58}, {"timestamp": "2026-04-27T04:09:40.929772", "incoming": 1226, "outgoing": 691}, {"timestamp": "2026-04-27T04:09:42.253222", "incoming": 712, "outgoing": 560}, {"timestamp": "2026-04-27T04:09:43.746448", "incoming": 323, "outgoing": 609}, {"timestamp": "2026-04-27T04:09:44.798879", "incoming": 879, "outgoing": 534}, {"timestamp": "2026-04-27T04:09:45.834480", "incoming": 269, "outgoing": 148}, {"timestamp": "2026-04-27T04:09:46.885070", "incoming": 1429, "outgoing": 708}, {"timestamp": "2026-04-27T04:09:47.931602", "incoming": 681, "outgoing": 426}, {"timestamp": "2026-04-27T04:09:48.986906", "incoming": 681, "outgoing": 62}, {"timestamp": "2026-04-27T04:09:50.049299", "incoming": 393, "outgoing": 263}, {"timestamp": "2026-04-27T04:09:52.269402", "incoming": 522, "outgoing": 393}, {"timestamp": "2026-04-27T04:09:56.192099", "incoming": 1023, "outgoing": 281}, {"timestamp": "2026-04-27T04:09:58.291386", "incoming": 764, "outgoing": 116}, {"timestamp": "2026-04-27T04:10:00.166901", "incoming": 235, "outgoing": 700}, {"timestamp": "2026-04-27T04:10:01.814650", "incoming": 778, "outgoing": 381}, {"timestamp": "2026-04-27T04:10:03.036831", "incoming": 1240, "outgoing": 404}, {"timestamp": "2026-04-27T04:10:04.717790", "incoming": 488, "outgoing": 345}, {"timestamp": "2026-04-27T04:10:05.842384", "incoming": 704, "outgoing": 529}, {"timestamp": "2026-04-27T04:10:07.081069", "incoming": 207, "outgoing": 464}, {"timestamp": "2026-04-27T04:10:08.124734", "incoming": 482, "outgoing": 138}, {"timestamp": "2026-04-27T04:10:09.166140", "incoming": 975, "outgoing": 402}, {"timestamp": "2026-04-27T04:10:10.469509", "incoming": 189, "outgoing": 432}, {"timestamp": "2026-04-27T04:10:11.523404", "incoming": 661, "outgoing": 657}, {"timestamp": "2026-04-27T04:10:12.569872", "incoming": 600, "outgoing": 162}, {"timestamp": "2026-04-27T04:10:13.615940", "incoming": 108, "outgoing": 381}, {"timestamp": "2026-04-27T04:10:14.663661", "incoming": 719, "outgoing": 269}, {"timestamp": "2026-04-27T04:10:15.714259", "incoming": 501, "outgoing": 72}, {"timestamp": "2026-04-27T04:10:16.760101", "incoming": 317, "outgoing": 437}, {"timestamp": "2026-04-27T04:10:17.802254", "incoming": 641, "outgoing": 764}, {"timestamp": "2026-04-27T04:10:18.852889", "incoming": 663, "outgoing": 538}, {"timestamp": "2026-04-27T04:10:20.261268", "incoming": 692, "outgoing": 533}, {"timestamp": "2026-04-27T04:10:21.289296", "incoming": 809, "outgoing": 766}, {"timestamp": "2026-04-27T04:10:22.326757", "incoming": 1099, "outgoing": 581}, {"timestamp": "2026-04-27T04:10:23.354179", "incoming": 1109, "outgoing": 299}, {"timestamp": "2026-04-27T04:10:24.411934", "incoming": 962, "outgoing": 609}, {"timestamp": "2026-04-27T04:10:25.471826", "incoming": 427, "outgoing": 713}, {"timestamp": "2026-04-27T04:10:26.504209", "incoming": 854, "outgoing": 748}, {"timestamp": "2026-04-27T04:10:27.555338", "incoming": 1434, "outgoing": 465}, {"timestamp": "2026-04-27T04:10:28.578810", "incoming": 1448, "outgoing": 396}, {"timestamp": "2026-04-27T04:10:29.648238", "incoming": 216, "outgoing": 220}, {"timestamp": "2026-04-27T04:10:31.535670", "incoming": 830, "outgoing": 654}, {"timestamp": "2026-04-27T04:10:33.001872", "incoming": 1102, "outgoing": 646}, {"timestamp": "2026-04-27T04:10:34.065472", "incoming": 741, "outgoing": 603}, {"timestamp": "2026-04-27T04:10:35.106320", "incoming": 1388, "outgoing": 487}, {"timestamp": "2026-04-27T04:10:36.186308", "incoming": 1462, "outgoing": 589}, {"timestamp": "2026-04-27T04:10:37.221926", "incoming": 105, "outgoing": 95}, {"timestamp": "2026-04-27T04:24:25.946304", "incoming": 1043, "outgoing": 326}, {"timestamp": "2026-04-27T04:24:26.977858", "incoming": 470, "outgoing": 155}, {"timestamp": "2026-04-27T04:24:28.014497", "incoming": 822, "outgoing": 76}, {"timestamp": "2026-04-27T04:24:29.075999", "incoming": 616, "outgoing": 573}, {"timestamp": "2026-04-27T04:24:30.113462", "incoming": 837, "outgoing": 631}, {"timestamp": "2026-04-27T04:24:31.187560", "incoming": 436, "outgoing": 747}, {"timestamp": "2026-04-27T04:24:32.218244", "incoming": 412, "outgoing": 681}, {"timestamp": "2026-04-27T04:24:33.261134", "incoming": 416, "outgoing": 447}, {"timestamp": "2026-04-27T04:24:34.382275", "incoming": 1322, "outgoing": 174}, {"timestamp": "2026-04-27T04:24:35.433379", "incoming": 436, "outgoing": 173}, {"timestamp": "2026-04-27T04:24:36.595777", "incoming": 104, "outgoing": 495}, {"timestamp": "2026-04-27T04:24:37.679517", "incoming": 1343, "outgoing": 188}, {"timestamp": "2026-04-27T04:24:39.065367", "incoming": 1294, "outgoing": 576}, {"timestamp": "2026-04-27T04:24:40.106458", "incoming": 1027, "outgoing": 372}, {"timestamp": "2026-04-27T04:24:41.149216", "incoming": 890, "outgoing": 205}, {"timestamp": "2026-04-27T04:24:42.318184", "incoming": 263, "outgoing": 583}, {"timestamp": "2026-04-27T04:24:43.623383", "incoming": 169, "outgoing": 730}, {"timestamp": "2026-04-27T04:24:44.672373", "incoming": 856, "outgoing": 542}, {"timestamp": "2026-04-27T04:24:45.749226", "incoming": 1014, "outgoing": 531}, {"timestamp": "2026-04-27T04:24:47.248107", "incoming": 566, "outgoing": 644}, {"timestamp": "2026-04-27T04:24:48.282566", "incoming": 739, "outgoing": 791}, {"timestamp": "2026-04-27T04:24:49.333298", "incoming": 553, "outgoing": 358}, {"timestamp": "2026-04-27T04:24:50.374112", "incoming": 1122, "outgoing": 120}, {"timestamp": "2026-04-27T04:24:51.417595", "incoming": 1174, "outgoing": 732}, {"timestamp": "2026-04-27T04:24:52.454611", "incoming": 1483, "outgoing": 451}, {"timestamp": "2026-04-27T04:24:53.518524", "incoming": 1047, "outgoing": 372}, {"timestamp": "2026-04-27T04:24:54.650082", "incoming": 1220, "outgoing": 443}, {"timestamp": "2026-04-27T04:24:56.106826", "incoming": 252, "outgoing": 294}, {"timestamp": "2026-04-27T04:24:57.451959", "incoming": 527, "outgoing": 139}, {"timestamp": "2026-04-27T04:24:59.452499", "incoming": 1165, "outgoing": 93}, {"timestamp": "2026-04-27T04:25:01.348656", "incoming": 189, "outgoing": 263}, {"timestamp": "2026-04-27T04:25:02.755579", "incoming": 1253, "outgoing": 91}, {"timestamp": "2026-04-27T04:25:04.290982", "incoming": 818, "outgoing": 180}, {"timestamp": "2026-04-27T04:25:05.349487", "incoming": 1090, "outgoing": 250}, {"timestamp": "2026-04-27T04:25:06.781414", "incoming": 897, "outgoing": 197}, {"timestamp": "2026-04-27T04:25:07.839670", "incoming": 1023, "outgoing": 245}, {"timestamp": "2026-04-27T04:25:08.900881", "incoming": 1429, "outgoing": 137}, {"timestamp": "2026-04-27T04:25:10.079872", "incoming": 800, "outgoing": 776}, {"timestamp": "2026-04-27T04:25:11.117884", "incoming": 1390, "outgoing": 523}, {"timestamp": "2026-04-27T04:25:12.155366", "incoming": 904, "outgoing": 637}, {"timestamp": "2026-04-27T04:25:13.206952", "incoming": 1040, "outgoing": 731}, {"timestamp": "2026-04-27T04:25:14.412588", "incoming": 939, "outgoing": 352}, {"timestamp": "2026-04-27T04:25:16.207810", "incoming": 1358, "outgoing": 558}, {"timestamp": "2026-04-27T04:25:17.605265", "incoming": 441, "outgoing": 114}, {"timestamp": "2026-04-27T04:25:18.656737", "incoming": 1086, "outgoing": 207}, {"timestamp": "2026-04-27T04:25:19.722151", "incoming": 323, "outgoing": 341}, {"timestamp": "2026-04-27T04:25:20.772275", "incoming": 533, "outgoing": 552}, {"timestamp": "2026-04-27T04:25:21.989058", "incoming": 889, "outgoing": 651}, {"timestamp": "2026-04-27T04:25:23.456420", "incoming": 1326, "outgoing": 544}, {"timestamp": "2026-04-27T04:25:24.669249", "incoming": 1467, "outgoing": 347}, {"timestamp": "2026-04-27T04:25:25.904676", "incoming": 867, "outgoing": 243}, {"timestamp": "2026-04-27T04:25:26.954425", "incoming": 749, "outgoing": 603}, {"timestamp": "2026-04-27T04:25:28.044993", "incoming": 942, "outgoing": 482}, {"timestamp": "2026-04-27T04:25:29.303372", "incoming": 365, "outgoing": 395}, {"timestamp": "2026-04-27T04:25:30.373504", "incoming": 548, "outgoing": 534}, {"timestamp": "2026-04-27T04:25:31.405308", "incoming": 452, "outgoing": 332}, {"timestamp": "2026-04-27T04:25:32.441275", "incoming": 1027, "outgoing": 636}, {"timestamp": "2026-04-27T04:25:33.487558", "incoming": 433, "outgoing": 130}, {"timestamp": "2026-04-27T04:25:34.715995", "incoming": 221, "outgoing": 612}, {"timestamp": "2026-04-27T04:25:35.749276", "incoming": 945, "outgoing": 587}, {"timestamp": "2026-04-27T04:25:36.778944", "incoming": 743, "outgoing": 139}, {"timestamp": "2026-04-27T04:25:37.820517", "incoming": 361, "outgoing": 786}, {"timestamp": "2026-04-27T04:25:38.859101", "incoming": 1226, "outgoing": 480}, {"timestamp": "2026-04-27T04:25:39.893532", "incoming": 1299, "outgoing": 698}, {"timestamp": "2026-04-27T04:25:40.972221", "incoming": 306, "outgoing": 305}, {"timestamp": "2026-04-27T04:25:42.018132", "incoming": 720, "outgoing": 270}, {"timestamp": "2026-04-27T04:25:43.071687", "incoming": 322, "outgoing": 595}, {"timestamp": "2026-04-27T04:25:44.115173", "incoming": 1328, "outgoing": 607}, {"timestamp": "2026-04-27T04:25:45.151211", "incoming": 753, "outgoing": 125}, {"timestamp": "2026-04-27T04:25:46.187774", "incoming": 1310, "outgoing": 553}, {"timestamp": "2026-04-27T04:25:47.237205", "incoming": 343, "outgoing": 755}, {"timestamp": "2026-04-27T04:25:48.279496", "incoming": 265, "outgoing": 710}, {"timestamp": "2026-04-27T04:25:49.317039", "incoming": 1365, "outgoing": 295}, {"timestamp": "2026-04-27T04:25:50.360827", "incoming": 473, "outgoing": 365}, {"timestamp": "2026-04-27T04:25:51.392135", "incoming": 187, "outgoing": 231}, {"timestamp": "2026-04-27T04:25:52.426506", "incoming": 938, "outgoing": 95}, {"timestamp": "2026-04-27T04:25:53.457055", "incoming": 341, "outgoing": 776}, {"timestamp": "2026-04-27T04:25:54.490671", "incoming": 916, "outgoing": 580}, {"timestamp": "2026-04-27T04:25:55.523173", "incoming": 791, "outgoing": 359}, {"timestamp": "2026-04-27T04:25:56.561286", "incoming": 1227, "outgoing": 761}, {"timestamp": "2026-04-27T04:25:57.596182", "incoming": 617, "outgoing": 501}, {"timestamp": "2026-04-27T04:25:58.635660", "incoming": 604, "outgoing": 623}, {"timestamp": "2026-04-27T04:25:59.673222", "incoming": 1361, "outgoing": 464}, {"timestamp": "2026-04-27T04:26:00.705855", "incoming": 510, "outgoing": 426}, {"timestamp": "2026-04-27T04:26:01.748240", "incoming": 1193, "outgoing": 609}, {"timestamp": "2026-04-27T04:26:02.788604", "incoming": 203, "outgoing": 511}, {"timestamp": "2026-04-27T04:26:03.836652", "incoming": 763, "outgoing": 475}, {"timestamp": "2026-04-27T04:26:04.864551", "incoming": 951, "outgoing": 428}, {"timestamp": "2026-04-27T04:26:05.901617", "incoming": 535, "outgoing": 184}, {"timestamp": "2026-04-27T04:26:11.615810", "incoming": 1486, "outgoing": 631}, {"timestamp": "2026-04-27T04:26:12.648719", "incoming": 1433, "outgoing": 556}, {"timestamp": "2026-04-27T04:26:13.687180", "incoming": 104, "outgoing": 242}, {"timestamp": "2026-04-27T04:26:14.730127", "incoming": 256, "outgoing": 724}, {"timestamp": "2026-04-27T04:26:15.768513", "incoming": 326, "outgoing": 642}, {"timestamp": "2026-04-27T04:26:16.811280", "incoming": 1110, "outgoing": 200}, {"timestamp": "2026-04-27T04:26:17.846437", "incoming": 201, "outgoing": 671}, {"timestamp": "2026-04-27T04:26:18.874911", "incoming": 1456, "outgoing": 93}, {"timestamp": "2026-04-27T04:26:19.903834", "incoming": 347, "outgoing": 90}, {"timestamp": "2026-04-27T04:26:20.934295", "incoming": 153, "outgoing": 496}, {"timestamp": "2026-04-27T04:26:21.964336", "incoming": 1298, "outgoing": 524}, {"timestamp": "2026-04-27T04:26:22.992025", "incoming": 709, "outgoing": 644}, {"timestamp": "2026-04-27T04:26:24.025746", "incoming": 828, "outgoing": 257}, {"timestamp": "2026-04-27T04:26:25.062574", "incoming": 325, "outgoing": 377}, {"timestamp": "2026-04-27T04:26:26.108549", "incoming": 891, "outgoing": 475}, {"timestamp": "2026-04-27T04:26:27.143077", "incoming": 590, "outgoing": 476}, {"timestamp": "2026-04-27T04:26:28.185704", "incoming": 937, "outgoing": 790}, {"timestamp": "2026-04-27T04:26:29.229598", "incoming": 1174, "outgoing": 662}, {"timestamp": "2026-04-27T04:26:30.271349", "incoming": 650, "outgoing": 168}, {"timestamp": "2026-04-27T04:26:31.302419", "incoming": 1426, "outgoing": 692}, {"timestamp": "2026-04-27T04:26:32.338782", "incoming": 528, "outgoing": 254}, {"timestamp": "2026-04-27T04:26:33.372886", "incoming": 113, "outgoing": 623}, {"timestamp": "2026-04-27T04:26:34.417028", "incoming": 350, "outgoing": 776}, {"timestamp": "2026-04-27T04:26:35.450049", "incoming": 771, "outgoing": 397}, {"timestamp": "2026-04-27T04:26:36.489454", "incoming": 442, "outgoing": 432}, {"timestamp": "2026-04-27T04:26:37.520913", "incoming": 295, "outgoing": 106}, {"timestamp": "2026-04-27T04:26:38.551630", "incoming": 685, "outgoing": 137}, {"timestamp": "2026-04-27T04:26:39.580115", "incoming": 709, "outgoing": 401}, {"timestamp": "2026-04-27T04:26:40.630599", "incoming": 1486, "outgoing": 225}, {"timestamp": "2026-04-27T04:26:41.663618", "incoming": 982, "outgoing": 766}, {"timestamp": "2026-04-27T04:26:42.698705", "incoming": 956, "outgoing": 320}, {"timestamp": "2026-04-27T04:26:43.729973", "incoming": 972, "outgoing": 588}, {"timestamp": "2026-04-27T04:26:44.755580", "incoming": 1425, "outgoing": 786}, {"timestamp": "2026-04-27T04:26:45.786264", "incoming": 152, "outgoing": 163}, {"timestamp": "2026-04-27T04:26:47.273230", "incoming": 866, "outgoing": 363}, {"timestamp": "2026-04-27T04:26:48.818803", "incoming": 619, "outgoing": 243}, {"timestamp": "2026-04-27T04:26:49.864402", "incoming": 1119, "outgoing": 115}, {"timestamp": "2026-04-27T04:26:51.075130", "incoming": 377, "outgoing": 389}, {"timestamp": "2026-04-27T04:26:52.237426", "incoming": 286, "outgoing": 635}, {"timestamp": "2026-04-27T04:26:53.288030", "incoming": 140, "outgoing": 84}, {"timestamp": "2026-04-27T04:26:54.469226", "incoming": 325, "outgoing": 505}, {"timestamp": "2026-04-27T04:26:55.502848", "incoming": 569, "outgoing": 689}, {"timestamp": "2026-04-27T04:26:56.539785", "incoming": 1310, "outgoing": 490}, {"timestamp": "2026-04-27T04:26:57.575740", "incoming": 927, "outgoing": 462}, {"timestamp": "2026-04-27T04:26:58.795536", "incoming": 1455, "outgoing": 652}, {"timestamp": "2026-04-27T04:26:59.863329", "incoming": 1092, "outgoing": 172}, {"timestamp": "2026-04-27T04:27:01.598457", "incoming": 352, "outgoing": 346}, {"timestamp": "2026-04-27T04:27:02.713144", "incoming": 534, "outgoing": 119}, {"timestamp": "2026-04-27T04:27:04.026630", "incoming": 542, "outgoing": 443}, {"timestamp": "2026-04-27T04:27:05.194421", "incoming": 1310, "outgoing": 367}, {"timestamp": "2026-04-27T04:27:06.456691", "incoming": 725, "outgoing": 662}, {"timestamp": "2026-04-27T04:27:07.531909", "incoming": 882, "outgoing": 149}, {"timestamp": "2026-04-27T04:27:08.847874", "incoming": 860, "outgoing": 690}, {"timestamp": "2026-04-27T04:27:10.147214", "incoming": 1211, "outgoing": 253}, {"timestamp": "2026-04-27T04:27:11.184922", "incoming": 1127, "outgoing": 711}, {"timestamp": "2026-04-27T04:27:12.216096", "incoming": 1139, "outgoing": 543}, {"timestamp": "2026-04-27T04:27:13.329320", "incoming": 673, "outgoing": 95}, {"timestamp": "2026-04-27T04:27:14.607787", "incoming": 606, "outgoing": 725}, {"timestamp": "2026-04-27T04:27:16.164325", "incoming": 824, "outgoing": 725}, {"timestamp": "2026-04-27T04:27:17.204033", "incoming": 1464, "outgoing": 765}, {"timestamp": "2026-04-27T04:27:18.254811", "incoming": 912, "outgoing": 389}, {"timestamp": "2026-04-27T04:27:19.302210", "incoming": 1203, "outgoing": 76}, {"timestamp": "2026-04-27T04:27:20.344194", "incoming": 1371, "outgoing": 400}, {"timestamp": "2026-04-27T04:27:21.430472", "incoming": 1026, "outgoing": 209}, {"timestamp": "2026-04-27T04:27:22.762882", "incoming": 365, "outgoing": 94}, {"timestamp": "2026-04-27T04:27:23.795646", "incoming": 737, "outgoing": 235}, {"timestamp": "2026-04-27T04:27:24.881179", "incoming": 1355, "outgoing": 308}, {"timestamp": "2026-04-27T04:27:25.922702", "incoming": 1360, "outgoing": 603}, {"timestamp": "2026-04-27T04:27:26.995107", "incoming": 852, "outgoing": 217}, {"timestamp": "2026-04-27T04:27:28.052635", "incoming": 840, "outgoing": 466}, {"timestamp": "2026-04-27T04:27:29.282806", "incoming": 230, "outgoing": 433}, {"timestamp": "2026-04-27T04:27:30.723478", "incoming": 1433, "outgoing": 236}, {"timestamp": "2026-04-27T04:27:31.853942", "incoming": 747, "outgoing": 532}, {"timestamp": "2026-04-27T04:27:33.150956", "incoming": 393, "outgoing": 635}, {"timestamp": "2026-04-27T04:27:35.476640", "incoming": 900, "outgoing": 225}, {"timestamp": "2026-04-27T04:27:36.567395", "incoming": 196, "outgoing": 505}, {"timestamp": "2026-04-27T04:27:38.101928", "incoming": 933, "outgoing": 709}, {"timestamp": "2026-04-27T04:27:40.084197", "incoming": 1168, "outgoing": 83}, {"timestamp": "2026-04-27T04:27:41.446977", "incoming": 1418, "outgoing": 755}, {"timestamp": "2026-04-27T04:27:43.369500", "incoming": 1154, "outgoing": 212}, {"timestamp": "2026-04-27T04:27:44.587006", "incoming": 1170, "outgoing": 368}, {"timestamp": "2026-04-27T04:27:45.628082", "incoming": 843, "outgoing": 654}, {"timestamp": "2026-04-27T04:27:46.682209", "incoming": 1137, "outgoing": 223}, {"timestamp": "2026-04-27T04:27:47.799816", "incoming": 1306, "outgoing": 737}, {"timestamp": "2026-04-27T04:27:48.844207", "incoming": 601, "outgoing": 380}, {"timestamp": "2026-04-27T04:27:49.986071", "incoming": 723, "outgoing": 792}, {"timestamp": "2026-04-27T04:27:51.062137", "incoming": 1430, "outgoing": 206}, {"timestamp": "2026-04-27T04:27:52.228092", "incoming": 224, "outgoing": 718}, {"timestamp": "2026-04-27T04:27:53.268699", "incoming": 375, "outgoing": 122}, {"timestamp": "2026-04-27T04:27:54.535387", "incoming": 1000, "outgoing": 646}, {"timestamp": "2026-04-27T04:27:55.582798", "incoming": 767, "outgoing": 706}, {"timestamp": "2026-04-27T04:27:56.634478", "incoming": 691, "outgoing": 585}, {"timestamp": "2026-04-27T04:27:57.684939", "incoming": 1340, "outgoing": 80}, {"timestamp": "2026-04-27T04:28:00.073955", "incoming": 714, "outgoing": 613}, {"timestamp": "2026-04-27T04:28:01.780568", "incoming": 102, "outgoing": 103}, {"timestamp": "2026-04-27T04:28:03.186481", "incoming": 1476, "outgoing": 106}, {"timestamp": "2026-04-27T04:28:05.467860", "incoming": 349, "outgoing": 749}, {"timestamp": "2026-04-27T04:28:07.028726", "incoming": 215, "outgoing": 183}, {"timestamp": "2026-04-27T04:28:09.749908", "incoming": 1137, "outgoing": 749}, {"timestamp": "2026-04-27T04:28:12.009824", "incoming": 238, "outgoing": 546}, {"timestamp": "2026-04-27T04:28:13.184597", "incoming": 1224, "outgoing": 724}, {"timestamp": "2026-04-27T04:28:14.230315", "incoming": 987, "outgoing": 388}, {"timestamp": "2026-04-27T04:28:15.263512", "incoming": 1051, "outgoing": 348}, {"timestamp": "2026-04-27T04:28:16.306333", "incoming": 345, "outgoing": 525}, {"timestamp": "2026-04-27T04:28:17.348607", "incoming": 960, "outgoing": 56}, {"timestamp": "2026-04-27T04:28:18.591602", "incoming": 1466, "outgoing": 475}, {"timestamp": "2026-04-27T04:28:19.633285", "incoming": 1408, "outgoing": 253}, {"timestamp": "2026-04-27T04:28:20.669275", "incoming": 1399, "outgoing": 165}, {"timestamp": "2026-04-27T04:28:21.710688", "incoming": 743, "outgoing": 484}, {"timestamp": "2026-04-27T04:28:22.762993", "incoming": 469, "outgoing": 328}, {"timestamp": "2026-04-27T04:28:24.098982", "incoming": 370, "outgoing": 524}, {"timestamp": "2026-04-27T04:28:26.217544", "incoming": 478, "outgoing": 367}, {"timestamp": "2026-04-27T04:28:28.085065", "incoming": 375, "outgoing": 439}, {"timestamp": "2026-04-27T04:28:30.436424", "incoming": 232, "outgoing": 536}, {"timestamp": "2026-04-27T04:28:32.061128", "incoming": 418, "outgoing": 379}, {"timestamp": "2026-04-27T04:28:33.968175", "incoming": 206, "outgoing": 344}, {"timestamp": "2026-04-27T04:28:36.309111", "incoming": 1098, "outgoing": 71}, {"timestamp": "2026-04-27T04:28:38.568752", "incoming": 302, "outgoing": 510}, {"timestamp": "2026-04-27T04:28:41.525012", "incoming": 301, "outgoing": 224}, {"timestamp": "2026-04-27T04:28:43.136632", "incoming": 962, "outgoing": 75}, {"timestamp": "2026-04-27T04:28:45.380637", "incoming": 591, "outgoing": 619}, {"timestamp": "2026-04-27T04:28:46.619193", "incoming": 1235, "outgoing": 536}, {"timestamp": "2026-04-27T04:28:47.671687", "incoming": 1045, "outgoing": 537}, {"timestamp": "2026-04-27T04:28:48.709192", "incoming": 662, "outgoing": 503}, {"timestamp": "2026-04-27T04:28:49.753557", "incoming": 1488, "outgoing": 380}, {"timestamp": "2026-04-27T04:28:50.811444", "incoming": 684, "outgoing": 345}, {"timestamp": "2026-04-27T04:28:51.930972", "incoming": 1460, "outgoing": 141}, {"timestamp": "2026-04-27T04:28:53.194187", "incoming": 687, "outgoing": 59}, {"timestamp": "2026-04-27T04:28:54.239680", "incoming": 257, "outgoing": 300}, {"timestamp": "2026-04-27T04:28:55.301942", "incoming": 282, "outgoing": 603}, {"timestamp": "2026-04-27T04:28:56.344182", "incoming": 167, "outgoing": 98}, {"timestamp": "2026-04-27T04:28:57.380050", "incoming": 1032, "outgoing": 680}, {"timestamp": "2026-04-27T04:28:58.416916", "incoming": 146, "outgoing": 125}, {"timestamp": "2026-04-27T04:28:59.461005", "incoming": 376, "outgoing": 715}, {"timestamp": "2026-04-27T04:29:00.503189", "incoming": 780, "outgoing": 463}, {"timestamp": "2026-04-27T04:29:01.564719", "incoming": 552, "outgoing": 293}, {"timestamp": "2026-04-27T04:29:02.606045", "incoming": 564, "outgoing": 696}, {"timestamp": "2026-04-27T04:29:03.646655", "incoming": 1027, "outgoing": 379}, {"timestamp": "2026-04-27T04:29:04.757765", "incoming": 362, "outgoing": 774}, {"timestamp": "2026-04-27T04:29:07.529680", "incoming": 420, "outgoing": 393}, {"timestamp": "2026-04-27T04:29:08.615780", "incoming": 824, "outgoing": 647}, {"timestamp": "2026-04-27T04:29:09.670764", "incoming": 1500, "outgoing": 268}, {"timestamp": "2026-04-27T04:29:10.736348", "incoming": 1333, "outgoing": 567}, {"timestamp": "2026-04-27T04:29:11.796975", "incoming": 319, "outgoing": 666}, {"timestamp": "2026-04-27T04:29:12.896906", "incoming": 215, "outgoing": 389}, {"timestamp": "2026-04-27T04:29:14.062754", "incoming": 1233, "outgoing": 184}, {"timestamp": "2026-04-27T04:29:15.099309", "incoming": 378, "outgoing": 324}, {"timestamp": "2026-04-27T04:29:16.163115", "incoming": 302, "outgoing": 437}, {"timestamp": "2026-04-27T04:29:17.643305", "incoming": 753, "outgoing": 637}, {"timestamp": "2026-04-27T04:29:19.502403", "incoming": 618, "outgoing": 641}, {"timestamp": "2026-04-27T04:29:20.968120", "incoming": 894, "outgoing": 283}, {"timestamp": "2026-04-27T04:29:22.276573", "incoming": 1169, "outgoing": 665}, {"timestamp": "2026-04-27T04:29:23.454369", "incoming": 1093, "outgoing": 504}, {"timestamp": "2026-04-27T04:29:25.055231", "incoming": 553, "outgoing": 749}, {"timestamp": "2026-04-27T04:29:26.375162", "incoming": 362, "outgoing": 684}, {"timestamp": "2026-04-27T04:29:28.501855", "incoming": 399, "outgoing": 601}, {"timestamp": "2026-04-27T04:29:29.588748", "incoming": 1396, "outgoing": 542}, {"timestamp": "2026-04-27T04:29:30.621509", "incoming": 807, "outgoing": 752}, {"timestamp": "2026-04-27T04:29:31.662860", "incoming": 153, "outgoing": 473}, {"timestamp": "2026-04-27T04:29:32.697195", "incoming": 907, "outgoing": 799}, {"timestamp": "2026-04-27T04:29:33.733107", "incoming": 1101, "outgoing": 109}, {"timestamp": "2026-04-27T04:29:34.766388", "incoming": 1427, "outgoing": 644}, {"timestamp": "2026-04-27T04:29:35.816221", "incoming": 382, "outgoing": 83}], "protocol_stats": {"TCP": 1558, "UDP": 1783, "HTTP": 1472, "HTTPS": 1567, "ICMP": 1668, "DNS": 1541, "Other": 1605}, "attack_stats": {"SQL\u6ce8\u5165": 29, "XSS\u653b\u51fb": 27, "DDoS\u653b\u51fb": 30, "\u7aef\u53e3\u626b\u63cf": 32, "\u66b4\u529b\u7834\u89e3": 26, "\u5f02\u5e38\u6d41\u91cf": 23, "\u75c5\u6bd2/\u6728\u9a6c": 30}, "ip_data": {"192.168.1.46": {"in_traffic": 669, "out_traffic": 281, "threats": 0, "last_seen": "2026-04-27T04:29:23.454369", "is_blocked": false}, "192.168.1.202": {"in_traffic": 562, "out_traffic": 172, "threats": 1, "last_seen": "2026-04-27T04:26:27.143077", "is_blocked": false}, "192.168.1.127": {"in_traffic": 888, "out_traffic": 427, "threats": 1, "last_seen": "2026-04-27T04:29:35.816221", "is_blocked": false}, "192.168.1.42": {"in_traffic": 907, "out_traffic": 459, "threats": 1, "last_seen": "2026-04-27T04:28:41.525012", "is_blocked": false}, "192.168.1.49": {"in_traffic": 585, "out_traffic": 295, "threats": 0, "last_seen": "2026-04-27T04:24:25.946304", "is_blocked": false}, "192.168.1.183": {"in_traffic": 445, "out_traffic": 289, "threats": 0, "last_seen": "2026-04-27T04:27:04.026630", "is_blocked": false}, "192.168.1.216": {"in_traffic": 918, "out_traffic": 436, "threats": 1, "last_seen": "2026-04-27T04:29:29.588748", "is_blocked": false}, "192.168.1.155": {"in_traffic": 1027, "out_traffic": 580, "threats": 2, "last_seen": "2026-04-27T04:27:53.268699", "is_blocked": false}, "192.168.1.217": {"in_traffic": 1146, "out_traffic": 439, "threats": 0, "last_seen": "2026-04-27T04:27:52.228092", "is_blocked": false}, "192.168.1.99": {"in_traffic": 734, "out_traffic": 393, "threats": 0, "last_seen": "2026-04-27T04:27:24.881179", "is_blocked": false}, "192.168.1.59": {"in_traffic": 1064, "out_traffic": 655, "threats": 0, "last_seen": "2026-04-27T04:29:31.662860", "is_blocked": false}, "192.168.1.92": {"in_traffic": 1047, "out_traffic": 389, "threats": 0, "last_seen": "2026-04-27T04:28:53.194187", "is_blocked": false}, "192.168.1.246": {"in_traffic": 638, "out_traffic": 460, "threats": 0, "last_seen": "2026-04-27T04:29:26.375162", "is_blocked": false}, "192.168.1.134": {"in_traffic": 1107, "out_traffic": 521, "threats": 2, "last_seen": "2026-04-27T04:29:35.816221", "is_blocked": false}, "192.168.1.54": {"in_traffic": 620, "out_traffic": 365, "threats": 0, "last_seen": "2026-04-27T04:27:33.150956", "is_blocked": false}, "192.168.1.140": {"in_traffic": 665, "out_traffic": 339, "threats": 1, "last_seen": "2026-04-27T04:25:05.349487", "is_blocked": false}, "192.168.1.175": {"in_traffic": 989, "out_traffic": 488, "threats": 1, "last_seen": "2026-04-27T04:28:26.217544", "is_blocked": false}, "192.168.1.222": {"in_traffic": 686, "out_traffic": 254, "threats": 1, "last_seen": "2026-04-27T04:28:46.619193", "is_blocked": false}, "192.168.1.188": {"in_traffic": 520, "out_traffic": 178, "threats": 0, "last_seen": "2026-04-27T04:10:37.221926", "is_blocked": false}, "192.168.1.162": {"in_traffic": 618, "out_traffic": 354, "threats": 0, "last_seen": "2026-04-27T04:29:02.606045", "is_blocked": false}, "192.168.1.187": {"in_traffic": 986, "out_traffic": 601, "threats": 0, "last_seen": "2026-04-27T04:29:17.643305", "is_blocked": false}, "192.168.1.203": {"in_traffic": 926, "out_traffic": 309, "threats": 2, "last_seen": "2026-04-27T04:29:26.375162", "is_blocked": false}, "192.168.1.153": {"in_traffic": 500, "out_traffic": 337, "threats": 0, "last_seen": "2026-04-27T04:29:02.606045", "is_blocked": false}, "192.168.1.27": {"in_traffic": 841, "out_traffic": 435, "threats": 1, "last_seen": "2026-04-27T04:29:07.529680", "is_blocked": false}, "192.168.1.164": {"in_traffic": 429, "out_traffic": 258, "threats": 0, "last_seen": "2026-04-27T04:26:55.502848", "is_blocked": false}, "192.168.1.52": {"in_traffic": 959, "out_traffic": 390, "threats": 1, "last_seen": "2026-04-27T04:29:09.670764", "is_blocked": false}, "192.168.1.53": {"in_traffic": 637, "out_traffic": 477, "threats": 0, "last_seen": "2026-04-27T04:25:11.117884", "is_blocked": false}, "192.168.1.64": {"in_traffic": 694, "out_traffic": 447, "threats": 1, "last_seen": "2026-04-27T04:29:15.099309", "is_blocked": false}, "192.168.1.94": {"in_traffic": 1266, "out_traffic": 547, "threats": 1, "last_seen": "2026-04-27T04:28:24.098982", "is_blocked": false}, "192.168.1.86": {"in_traffic": 582, "out_traffic": 200, "threats": 3, "last_seen": "2026-04-27T04:29:20.968120", "is_blocked": false}, "192.168.1.247": {"in_traffic": 537, "out_traffic": 166, "threats": 0, "last_seen": "2026-04-27T04:29:04.757765", "is_blocked": false}, "192.168.1.204": {"in_traffic": 719, "out_traffic": 340, "threats": 1, "last_seen": "2026-04-27T04:28:50.811444", "is_blocked": false}, "192.168.1.103": {"in_traffic": 871, "out_traffic": 336, "threats": 0, "last_seen": "2026-04-27T04:29:11.796975", "is_blocked": false}, "192.168.1.88": {"in_traffic": 740, "out_traffic": 309, "threats": 1, "last_seen": "2026-04-27T04:26:59.863329", "is_blocked": false}, "192.168.1.4": {"in_traffic": 615, "out_traffic": 418, "threats": 0, "last_seen": "2026-04-27T04:27:07.531909", "is_blocked": false}, "192.168.1.111": {"in_traffic": 653, "out_traffic": 459, "threats": 3, "last_seen": "2026-04-27T04:27:38.101928", "is_blocked": false}, "192.168.1.151": {"in_traffic": 279, "out_traffic": 294, "threats": 1, "last_seen": "2026-04-27T04:28:49.753557", "is_blocked": false}, "192.168.1.177": {"in_traffic": 694, "out_traffic": 344, "threats": 2, "last_seen": "2026-04-27T04:28:07.028726", "is_blocked": false}, "192.168.1.10": {"in_traffic": 607, "out_traffic": 341, "threats": 0, "last_seen": "2026-04-27T04:29:01.564719", "is_blocked": false}, "192.168.1.72": {"in_traffic": 467, "out_traffic": 243, "threats": 1, "last_seen": "2026-04-27T04:25:48.279496", "is_blocked": false}, "192.168.1.221": {"in_traffic": 851, "out_traffic": 385, "threats": 3, "last_seen": "2026-04-27T04:29:17.643305", "is_blocked": false}, "192.168.1.47": {"in_traffic": 770, "out_traffic": 361, "threats": 0, "last_seen": "2026-04-27T04:28:54.239680", "is_blocked": false}, "192.168.1.51": {"in_traffic": 746, "out_traffic": 330, "threats": 1, "last_seen": "2026-04-27T04:29:28.501855", "is_blocked": false}, "192.168.1.241": {"in_traffic": 562, "out_traffic": 350, "threats": 1, "last_seen": "2026-04-27T04:27:21.430472", "is_blocked": false}, "192.168.1.96": {"in_traffic": 951, "out_traffic": 462, "threats": 1, "last_seen": "2026-04-27T04:29:17.643305", "is_blocked": false}, "192.168.1.133": {"in_traffic": 888, "out_traffic": 415, "threats": 1, "last_seen": "2026-04-27T04:29:29.588748", "is_blocked": false}, "192.168.1.174": {"in_traffic": 662, "out_traffic": 314, "threats": 0, "last_seen": "2026-04-27T04:29:31.662860", "is_blocked": false}, "192.168.1.157": {"in_traffic": 594, "out_traffic": 309, "threats": 0, "last_seen": "2026-04-27T04:26:28.185704", "is_blocked": false}, "192.168.1.15": {"in_traffic": 917, "out_traffic": 598, "threats": 2, "last_seen": "2026-04-27T04:29:30.621509", "is_blocked": false}, "192.168.1.172": {"in_traffic": 735, "out_traffic": 317, "threats": 0, "last_seen": "2026-04-27T04:28:12.009824", "is_blocked": false}, "192.168.1.141": {"in_traffic": 736, "out_traffic": 291, "threats": 1, "last_seen": "2026-04-27T04:29:15.099309", "is_blocked": false}, "192.168.1.80": {"in_traffic": 810, "out_traffic": 450, "threats": 4, "last_seen": "2026-04-27T04:29:23.454369", "is_blocked": false}, "192.168.1.28": {"in_traffic": 886, "out_traffic": 329, "threats": 1, "last_seen": "2026-04-27T04:28:30.436424", "is_blocked": false}, "192.168.1.81": {"in_traffic": 1107, "out_traffic": 478, "threats": 2, "last_seen": "2026-04-27T04:29:25.055231", "is_blocked": false}, "192.168.1.152": {"in_traffic": 801, "out_traffic": 488, "threats": 0, "last_seen": "2026-04-27T04:29:20.968120", "is_blocked": false}, "192.168.1.198": {"in_traffic": 937, "out_traffic": 397, "threats": 1, "last_seen": "2026-04-27T04:29:34.766388", "is_blocked": false}, "192.168.1.126": {"in_traffic": 385, "out_traffic": 139, "threats": 0, "last_seen": "2026-04-27T04:28:59.461005", "is_blocked": false}, "192.168.1.44": {"in_traffic": 685, "out_traffic": 303, "threats": 1, "last_seen": "2026-04-27T04:29:15.099309", "is_blocked": false}, "192.168.1.231": {"in_traffic": 734, "out_traffic": 474, "threats": 2, "last_seen": "2026-04-27T04:29:31.662860", "is_blocked": false}, "192.168.1.215": {"in_traffic": 1057, "out_traffic": 503, "threats": 0, "last_seen": "2026-04-27T04:28:24.098982", "is_blocked": false}, "192.168.1.124": {"in_traffic": 560, "out_traffic": 242, "threats": 2, "last_seen": "2026-04-27T04:29:26.375162", "is_blocked": false}, "192.168.1.132": {"in_traffic": 666, "out_traffic": 343, "threats": 0, "last_seen": "2026-04-27T04:29:07.529680", "is_blocked": false}, "192.168.1.8": {"in_traffic": 863, "out_traffic": 253, "threats": 0, "last_seen": "2026-04-27T04:29:17.643305", "is_blocked": false}, "192.168.1.93": {"in_traffic": 1028, "out_traffic": 336, "threats": 0, "last_seen": "2026-04-27T04:29:25.055231", "is_blocked": false}, "192.168.1.18": {"in_traffic": 558, "out_traffic": 371, "threats": 1, "last_seen": "2026-04-27T04:26:48.818803", "is_blocked": false}, "192.168.1.55": {"in_traffic": 578, "out_traffic": 329, "threats": 0, "last_seen": "2026-04-27T04:27:14.607787", "is_blocked": false}, "192.168.1.79": {"in_traffic": 653, "out_traffic": 354, "threats": 1, "last_seen": "2026-04-27T04:29:12.896906", "is_blocked": false}, "192.168.1.109": {"in_traffic": 522, "out_traffic": 243, "threats": 0, "last_seen": "2026-04-27T04:29:32.697195", "is_blocked": false}, "192.168.1.220": {"in_traffic": 833, "out_traffic": 496, "threats": 0, "last_seen": "2026-04-27T04:29:33.733107", "is_blocked": false}, "192.168.1.252": {"in_traffic": 780, "out_traffic": 314, "threats": 1, "last_seen": "2026-04-27T04:27:21.430472", "is_blocked": false}, "192.168.1.16": {"in_traffic": 777, "out_traffic": 369, "threats": 0, "last_seen": "2026-04-27T04:28:41.525012", "is_blocked": false}, "192.168.1.209": {"in_traffic": 709, "out_traffic": 274, "threats": 2, "last_seen": "2026-04-27T04:26:01.748240", "is_blocked": false}, "192.168.1.230": {"in_traffic": 929, "out_traffic": 446, "threats": 0, "last_seen": "2026-04-27T04:29:35.816221", "is_blocked": false}, "192.168.1.62": {"in_traffic": 561, "out_traffic": 308, "threats": 2, "last_seen": "2026-04-27T04:28:09.749908", "is_blocked": false}, "192.168.1.178": {"in_traffic": 736, "out_traffic": 401, "threats": 0, "last_seen": "2026-04-27T04:28:41.525012", "is_blocked": false}, "192.168.1.58": {"in_traffic": 631, "out_traffic": 356, "threats": 0, "last_seen": "2026-04-27T04:27:48.844207", "is_blocked": false}, "192.168.1.165": {"in_traffic": 939, "out_traffic": 526, "threats": 0, "last_seen": "2026-04-27T04:29:03.646655", "is_blocked": false}, "192.168.1.104": {"in_traffic": 848, "out_traffic": 454, "threats": 2, "last_seen": "2026-04-27T04:29:19.502403", "is_blocked": false}, "192.168.1.2": {"in_traffic": 488, "out_traffic": 262, "threats": 0, "last_seen": "2026-04-27T04:29:02.606045", "is_blocked": false}, "192.168.1.122": {"in_traffic": 575, "out_traffic": 364, "threats": 0, "last_seen": "2026-04-27T04:29:29.588748", "is_blocked": false}, "192.168.1.37": {"in_traffic": 450, "out_traffic": 291, "threats": 1, "last_seen": "2026-04-27T04:28:58.416916", "is_blocked": false}, "192.168.1.14": {"in_traffic": 592, "out_traffic": 210, "threats": 1, "last_seen": "2026-04-27T04:27:08.847874", "is_blocked": false}, "192.168.1.11": {"in_traffic": 793, "out_traffic": 453, "threats": 1, "last_seen": "2026-04-27T04:29:31.662860", "is_blocked": false}, "192.168.1.229": {"in_traffic": 988, "out_traffic": 527, "threats": 1, "last_seen": "2026-04-27T04:28:28.085065", "is_blocked": false}, "192.168.1.61": {"in_traffic": 614, "out_traffic": 247, "threats": 0, "last_seen": "2026-04-27T04:28:21.710688", "is_blocked": false}, "192.168.1.185": {"in_traffic": 849, "out_traffic": 425, "threats": 3, "last_seen": "2026-04-27T04:27:47.799816", "is_blocked": false}, "192.168.1.176": {"in_traffic": 907, "out_traffic": 506, "threats": 0, "last_seen": "2026-04-27T04:29:33.733107", "is_blocked": false}, "192.168.1.227": {"in_traffic": 706, "out_traffic": 305, "threats": 0, "last_seen": "2026-04-27T04:28:13.184597", "is_blocked": false}, "192.168.1.139": {"in_traffic": 579, "out_traffic": 315, "threats": 1, "last_seen": "2026-04-27T04:28:58.416916", "is_blocked": false}, "192.168.1.218": {"in_traffic": 691, "out_traffic": 374, "threats": 0, "last_seen": "2026-04-27T04:28:24.098982", "is_blocked": false}, "192.168.1.173": {"in_traffic": 619, "out_traffic": 280, "threats": 2, "last_seen": "2026-04-27T04:29:30.621509", "is_blocked": false}, "192.168.1.199": {"in_traffic": 872, "out_traffic": 488, "threats": 0, "last_seen": "2026-04-27T04:29:11.796975", "is_blocked": false}, "192.168.1.200": {"in_traffic": 799, "out_traffic": 614, "threats": 1, "last_seen": "2026-04-27T04:29:34.766388", "is_blocked": false}, "192.168.1.32": {"in_traffic": 901, "out_traffic": 461, "threats": 1, "last_seen": "2026-04-27T04:29:08.615780", "is_blocked": false}, "192.168.1.194": {"in_traffic": 1164, "out_traffic": 533, "threats": 0, "last_seen": "2026-04-27T04:27:46.682209", "is_blocked": false}, "192.168.1.17": {"in_traffic": 676, "out_traffic": 376, "threats": 3, "last_seen": "2026-04-27T04:26:37.520913", "is_blocked": false}, "192.168.1.117": {"in_traffic": 523, "out_traffic": 267, "threats": 1, "last_seen": "2026-04-27T04:29:33.733107", "is_blocked": false}, "192.168.1.144": {"in_traffic": 570, "out_traffic": 219, "threats": 0, "last_seen": "2026-04-27T04:10:34.065472", "is_blocked": false}, "192.168.1.167": {"in_traffic": 443, "out_traffic": 279, "threats": 0, "last_seen": "2026-04-27T04:28:46.619193", "is_blocked": false}, "192.168.1.110": {"in_traffic": 1031, "out_traffic": 483, "threats": 0, "last_seen": "2026-04-27T04:28:15.263512", "is_blocked": false}, "192.168.1.75": {"in_traffic": 805, "out_traffic": 374, "threats": 0, "last_seen": "2026-04-27T04:29:22.276573", "is_blocked": false}, "192.168.1.65": {"in_traffic": 994, "out_traffic": 321, "threats": 0, "last_seen": "2026-04-27T04:29:15.099309", "is_blocked": false}, "192.168.1.116": {"in_traffic": 1032, "out_traffic": 615, "threats": 0, "last_seen": "2026-04-27T04:28:50.811444", "is_blocked": false}, "192.168.1.20": {"in_traffic": 670, "out_traffic": 485, "threats": 1, "last_seen": "2026-04-27T04:29:12.896906", "is_blocked": false}, "192.168.1.60": {"in_traffic": 864, "out_traffic": 341, "threats": 0, "last_seen": "2026-04-27T04:28:50.811444", "is_blocked": false}, "192.168.1.84": {"in_traffic": 761, "out_traffic": 290, "threats": 1, "last_seen": "2026-04-27T04:29:30.621509", "is_blocked": false}, "192.168.1.106": {"in_traffic": 612, "out_traffic": 282, "threats": 2, "last_seen": "2026-04-27T04:28:57.380050", "is_blocked": false}, "192.168.1.131": {"in_traffic": 484, "out_traffic": 290, "threats": 1, "last_seen": "2026-04-27T04:28:55.301942", "is_blocked": false}, "192.168.1.225": {"in_traffic": 714, "out_traffic": 282, "threats": 3, "last_seen": "2026-04-27T04:29:00.503189", "is_blocked": false}, "192.168.1.12": {"in_traffic": 607, "out_traffic": 394, "threats": 0, "last_seen": "2026-04-27T04:28:12.009824", "is_blocked": false}, "192.168.1.242": {"in_traffic": 550, "out_traffic": 353, "threats": 1, "last_seen": "2026-04-27T04:29:19.502403", "is_blocked": false}, "192.168.1.91": {"in_traffic": 711, "out_traffic": 308, "threats": 1, "last_seen": "2026-04-27T04:28:09.749908", "is_blocked": false}, "192.168.1.253": {"in_traffic": 947, "out_traffic": 451, "threats": 0, "last_seen": "2026-04-27T04:29:28.501855", "is_blocked": false}, "192.168.1.147": {"in_traffic": 598, "out_traffic": 274, "threats": 1, "last_seen": "2026-04-27T04:28:28.085065", "is_blocked": false}, "192.168.1.85": {"in_traffic": 592, "out_traffic": 231, "threats": 0, "last_seen": "2026-04-27T04:28:50.811444", "is_blocked": false}, "192.168.1.163": {"in_traffic": 663, "out_traffic": 365, "threats": 2, "last_seen": "2026-04-27T04:27:52.228092", "is_blocked": false}, "192.168.1.39": {"in_traffic": 596, "out_traffic": 336, "threats": 0, "last_seen": "2026-04-27T04:27:55.582798", "is_blocked": false}, "192.168.1.7": {"in_traffic": 789, "out_traffic": 450, "threats": 1, "last_seen": "2026-04-27T04:29:01.564719", "is_blocked": false}, "192.168.1.224": {"in_traffic": 616, "out_traffic": 388, "threats": 1, "last_seen": "2026-04-27T04:27:56.634478", "is_blocked": false}, "192.168.1.238": {"in_traffic": 813, "out_traffic": 376, "threats": 0, "last_seen": "2026-04-27T04:29:31.662860", "is_blocked": false}, "192.168.1.149": {"in_traffic": 686, "out_traffic": 354, "threats": 1, "last_seen": "2026-04-27T04:27:29.282806", "is_blocked": false}, "192.168.1.34": {"in_traffic": 793, "out_traffic": 357, "threats": 1, "last_seen": "2026-04-27T04:28:36.309111", "is_blocked": false}, "192.168.1.236": {"in_traffic": 483, "out_traffic": 221, "threats": 1, "last_seen": "2026-04-27T04:27:55.582798", "is_blocked": false}, "192.168.1.71": {"in_traffic": 509, "out_traffic": 313, "threats": 1, "last_seen": "2026-04-27T04:26:32.338782", "is_blocked": false}, "192.168.1.45": {"in_traffic": 740, "out_traffic": 319, "threats": 1, "last_seen": "2026-04-27T04:29:14.062754", "is_blocked": false}, "192.168.1.48": {"in_traffic": 351, "out_traffic": 123, "threats": 0, "last_seen": "2026-04-27T04:29:08.615780", "is_blocked": false}, "192.168.1.19": {"in_traffic": 1050, "out_traffic": 576, "threats": 0, "last_seen": "2026-04-27T04:29:01.564719", "is_blocked": false}, "192.168.1.148": {"in_traffic": 761, "out_traffic": 406, "threats": 1, "last_seen": "2026-04-27T04:29:23.454369", "is_blocked": false}, "192.168.1.181": {"in_traffic": 530, "out_traffic": 155, "threats": 0, "last_seen": "2026-04-27T04:29:35.816221", "is_blocked": false}, "192.168.1.154": {"in_traffic": 853, "out_traffic": 377, "threats": 2, "last_seen": "2026-04-27T04:28:53.194187", "is_blocked": false}, "192.168.1.143": {"in_traffic": 350, "out_traffic": 173, "threats": 0, "last_seen": "2026-04-27T04:24:57.451959", "is_blocked": false}, "192.168.1.232": {"in_traffic": 402, "out_traffic": 260, "threats": 3, "last_seen": "2026-04-27T04:28:07.028726", "is_blocked": false}, "192.168.1.36": {"in_traffic": 400, "out_traffic": 380, "threats": 0, "last_seen": "2026-04-27T04:29:00.503189", "is_blocked": false}, "192.168.1.207": {"in_traffic": 578, "out_traffic": 292, "threats": 0, "last_seen": "2026-04-27T04:29:33.733107", "is_blocked": false}, "192.168.1.206": {"in_traffic": 1022, "out_traffic": 487, "threats": 1, "last_seen": "2026-04-27T04:29:16.163115", "is_blocked": false}, "192.168.1.166": {"in_traffic": 704, "out_traffic": 480, "threats": 0, "last_seen": "2026-04-27T04:28:56.344182", "is_blocked": false}, "192.168.1.182": {"in_traffic": 799, "out_traffic": 447, "threats": 2, "last_seen": "2026-04-27T04:26:51.075130", "is_blocked": false}, "192.168.1.13": {"in_traffic": 582, "out_traffic": 297, "threats": 1, "last_seen": "2026-04-27T04:28:57.380050", "is_blocked": false}, "192.168.1.101": {"in_traffic": 535, "out_traffic": 315, "threats": 0, "last_seen": "2026-04-27T04:26:04.864551", "is_blocked": false}, "192.168.1.228": {"in_traffic": 812, "out_traffic": 438, "threats": 0, "last_seen": "2026-04-27T04:28:32.061128", "is_blocked": false}, "192.168.1.119": {"in_traffic": 955, "out_traffic": 384, "threats": 1, "last_seen": "2026-04-27T04:26:27.143077", "is_blocked": false}, "192.168.1.237": {"in_traffic": 852, "out_traffic": 359, "threats": 1, "last_seen": "2026-04-27T04:29:04.757765", "is_blocked": false}, "192.168.1.226": {"in_traffic": 444, "out_traffic": 187, "threats": 1, "last_seen": "2026-04-27T04:26:12.648719", "is_blocked": false}, "192.168.1.98": {"in_traffic": 755, "out_traffic": 336, "threats": 1, "last_seen": "2026-04-27T04:28:16.306333", "is_blocked": false}, "192.168.1.100": {"in_traffic": 537, "out_traffic": 198, "threats": 0, "last_seen": "2026-04-27T04:27:08.847874", "is_blocked": false}, "192.168.1.129": {"in_traffic": 650, "out_traffic": 360, "threats": 0, "last_seen": "2026-04-27T04:29:15.099309", "is_blocked": false}, "192.168.1.150": {"in_traffic": 335, "out_traffic": 257, "threats": 0, "last_seen": "2026-04-27T04:28:49.753557", "is_blocked": false}, "192.168.1.201": {"in_traffic": 654, "out_traffic": 425, "threats": 1, "last_seen": "2026-04-27T04:29:12.896906", "is_blocked": false}, "192.168.1.137": {"in_traffic": 733, "out_traffic": 364, "threats": 1, "last_seen": "2026-04-27T04:29:32.697195", "is_blocked": false}, "192.168.1.171": {"in_traffic": 379, "out_traffic": 258, "threats": 1, "last_seen": "2026-04-27T04:29:25.055231", "is_blocked": false}, "192.168.1.213": {"in_traffic": 412, "out_traffic": 214, "threats": 3, "last_seen": "2026-04-27T04:26:19.903834", "is_blocked": false}, "192.168.1.22": {"in_traffic": 669, "out_traffic": 313, "threats": 1, "last_seen": "2026-04-27T04:29:23.454369", "is_blocked": false}, "192.168.1.197": {"in_traffic": 431, "out_traffic": 111, "threats": 2, "last_seen": "2026-04-27T04:29:35.816221", "is_blocked": false}, "192.168.1.191": {"in_traffic": 650, "out_traffic": 491, "threats": 0, "last_seen": "2026-04-27T04:28:53.194187", "is_blocked": false}, "192.168.1.214": {"in_traffic": 544, "out_traffic": 264, "threats": 0, "last_seen": "2026-04-27T04:26:57.575740", "is_blocked": false}, "192.168.1.67": {"in_traffic": 718, "out_traffic": 351, "threats": 0, "last_seen": "2026-04-27T04:26:20.934295", "is_blocked": false}, "192.168.1.78": {"in_traffic": 500, "out_traffic": 342, "threats": 2, "last_seen": "2026-04-27T04:28:26.217544", "is_blocked": false}, "192.168.1.245": {"in_traffic": 960, "out_traffic": 511, "threats": 1, "last_seen": "2026-04-27T04:29:34.766388", "is_blocked": false}, "192.168.1.211": {"in_traffic": 777, "out_traffic": 528, "threats": 0, "last_seen": "2026-04-27T04:27:13.329320", "is_blocked": false}, "192.168.1.108": {"in_traffic": 402, "out_traffic": 258, "threats": 2, "last_seen": "2026-04-27T04:28:53.194187", "is_blocked": false}, "192.168.1.115": {"in_traffic": 520, "out_traffic": 263, "threats": 0, "last_seen": "2026-04-27T04:27:16.164325", "is_blocked": false}, "192.168.1.76": {"in_traffic": 606, "out_traffic": 353, "threats": 0, "last_seen": "2026-04-27T04:27:12.216096", "is_blocked": false}, "192.168.1.89": {"in_traffic": 359, "out_traffic": 221, "threats": 2, "last_seen": "2026-04-27T04:25:54.490671", "is_blocked": false}, "192.168.1.254": {"in_traffic": 524, "out_traffic": 367, "threats": 2, "last_seen": "2026-04-27T04:29:17.643305", "is_blocked": false}, "192.168.1.251": {"in_traffic": 363, "out_traffic": 191, "threats": 2, "last_seen": "2026-04-27T04:27:22.762882", "is_blocked": false}, "192.168.1.168": {"in_traffic": 664, "out_traffic": 248, "threats": 1, "last_seen": "2026-04-27T04:28:36.309111", "is_blocked": false}, "192.168.1.9": {"in_traffic": 638, "out_traffic": 332, "threats": 0, "last_seen": "2026-04-27T04:28:43.136632", "is_blocked": false}, "192.168.1.192": {"in_traffic": 574, "out_traffic": 297, "threats": 1, "last_seen": "2026-04-27T04:27:56.634478", "is_blocked": false}, "192.168.1.73": {"in_traffic": 479, "out_traffic": 278, "threats": 0, "last_seen": "2026-04-27T04:27:36.567395", "is_blocked": false}, "192.168.1.3": {"in_traffic": 603, "out_traffic": 358, "threats": 0, "last_seen": "2026-04-27T04:27:31.853942", "is_blocked": false}, "192.168.1.43": {"in_traffic": 481, "out_traffic": 260, "threats": 3, "last_seen": "2026-04-27T04:28:15.263512", "is_blocked": false}, "192.168.1.33": {"in_traffic": 163, "out_traffic": 109, "threats": 3, "last_seen": "2026-04-27T04:28:49.753557", "is_blocked": false}, "192.168.1.29": {"in_traffic": 998, "out_traffic": 574, "threats": 1, "last_seen": "2026-04-27T04:29:07.529680", "is_blocked": false}, "192.168.1.160": {"in_traffic": 728, "out_traffic": 455, "threats": 0, "last_seen": "2026-04-27T04:28:46.619193", "is_blocked": false}, "192.168.1.205": {"in_traffic": 570, "out_traffic": 282, "threats": 2, "last_seen": "2026-04-27T04:29:08.615780", "is_blocked": false}, "192.168.1.113": {"in_traffic": 244, "out_traffic": 220, "threats": 0, "last_seen": "2026-04-27T04:28:26.217544", "is_blocked": false}, "192.168.1.190": {"in_traffic": 544, "out_traffic": 366, "threats": 1, "last_seen": "2026-04-27T04:28:59.461005", "is_blocked": false}, "192.168.1.239": {"in_traffic": 469, "out_traffic": 265, "threats": 1, "last_seen": "2026-04-27T04:29:34.766388", "is_blocked": false}, "192.168.1.41": {"in_traffic": 907, "out_traffic": 509, "threats": 1, "last_seen": "2026-04-27T04:28:48.709192", "is_blocked": false}, "192.168.1.63": {"in_traffic": 482, "out_traffic": 204, "threats": 0, "last_seen": "2026-04-27T04:27:38.101928", "is_blocked": false}, "192.168.1.24": {"in_traffic": 523, "out_traffic": 249, "threats": 0, "last_seen": "2026-04-27T04:10:26.504209", "is_blocked": false}, "192.168.1.208": {"in_traffic": 666, "out_traffic": 377, "threats": 0, "last_seen": "2026-04-27T04:27:28.052635", "is_blocked": false}, "192.168.1.136": {"in_traffic": 525, "out_traffic": 207, "threats": 0, "last_seen": "2026-04-27T04:29:30.621509", "is_blocked": false}, "192.168.1.180": {"in_traffic": 345, "out_traffic": 271, "threats": 0, "last_seen": "2026-04-27T04:26:18.874911", "is_blocked": false}, "192.168.1.156": {"in_traffic": 456, "out_traffic": 242, "threats": 2, "last_seen": "2026-04-27T04:29:12.896906", "is_blocked": false}, "192.168.1.233": {"in_traffic": 755, "out_traffic": 312, "threats": 1, "last_seen": "2026-04-27T04:29:30.621509", "is_blocked": false}, "192.168.1.66": {"in_traffic": 1003, "out_traffic": 449, "threats": 0, "last_seen": "2026-04-27T04:29:34.766388", "is_blocked": false}, "192.168.1.118": {"in_traffic": 936, "out_traffic": 433, "threats": 0, "last_seen": "2026-04-27T04:29:28.501855", "is_blocked": false}, "192.168.1.234": {"in_traffic": 769, "out_traffic": 254, "threats": 0, "last_seen": "2026-04-27T04:27:38.101928", "is_blocked": false}, "192.168.1.105": {"in_traffic": 752, "out_traffic": 376, "threats": 2, "last_seen": "2026-04-27T04:28:19.633285", "is_blocked": false}, "192.168.1.77": {"in_traffic": 652, "out_traffic": 246, "threats": 1, "last_seen": "2026-04-27T04:28:54.239680", "is_blocked": false}, "192.168.1.223": {"in_traffic": 329, "out_traffic": 299, "threats": 0, "last_seen": "2026-04-27T04:28:43.136632", "is_blocked": false}, "192.168.1.158": {"in_traffic": 663, "out_traffic": 215, "threats": 2, "last_seen": "2026-04-27T04:26:56.539785", "is_blocked": false}, "192.168.1.179": {"in_traffic": 647, "out_traffic": 291, "threats": 2, "last_seen": "2026-04-27T04:29:22.276573", "is_blocked": false}, "192.168.1.212": {"in_traffic": 864, "out_traffic": 280, "threats": 0, "last_seen": "2026-04-27T04:29:26.375162", "is_blocked": false}, "192.168.1.195": {"in_traffic": 722, "out_traffic": 472, "threats": 0, "last_seen": "2026-04-27T04:28:12.009824", "is_blocked": false}, "192.168.1.135": {"in_traffic": 742, "out_traffic": 483, "threats": 0, "last_seen": "2026-04-27T04:28:21.710688", "is_blocked": false}, "192.168.1.21": {"in_traffic": 820, "out_traffic": 407, "threats": 0, "last_seen": "2026-04-27T04:28:38.568752", "is_blocked": false}, "192.168.1.83": {"in_traffic": 305, "out_traffic": 196, "threats": 1, "last_seen": "2026-04-27T04:28:28.085065", "is_blocked": false}, "192.168.1.112": {"in_traffic": 609, "out_traffic": 408, "threats": 0, "last_seen": "2026-04-27T04:29:20.968120", "is_blocked": false}, "192.168.1.6": {"in_traffic": 1113, "out_traffic": 631, "threats": 1, "last_seen": "2026-04-27T04:29:25.055231", "is_blocked": false}, "192.168.1.170": {"in_traffic": 471, "out_traffic": 221, "threats": 2, "last_seen": "2026-04-27T04:27:24.881179", "is_blocked": false}, "192.168.1.121": {"in_traffic": 649, "out_traffic": 216, "threats": 1, "last_seen": "2026-04-27T04:29:25.055231", "is_blocked": false}, "192.168.1.189": {"in_traffic": 441, "out_traffic": 204, "threats": 2, "last_seen": "2026-04-27T04:29:32.697195", "is_blocked": false}, "192.168.1.244": {"in_traffic": 482, "out_traffic": 260, "threats": 0, "last_seen": "2026-04-27T04:28:22.762993", "is_blocked": false}, "192.168.1.210": {"in_traffic": 399, "out_traffic": 285, "threats": 1, "last_seen": "2026-04-27T04:28:53.194187", "is_blocked": false}, "192.168.1.120": {"in_traffic": 659, "out_traffic": 247, "threats": 1, "last_seen": "2026-04-27T04:28:55.301942", "is_blocked": false}, "192.168.1.57": {"in_traffic": 346, "out_traffic": 201, "threats": 2, "last_seen": "2026-04-27T04:27:46.682209", "is_blocked": false}, "192.168.1.114": {"in_traffic": 264, "out_traffic": 222, "threats": 1, "last_seen": "2026-04-27T04:28:19.633285", "is_blocked": false}, "192.168.1.128": {"in_traffic": 467, "out_traffic": 285, "threats": 1, "last_seen": "2026-04-27T04:28:43.136632", "is_blocked": false}, "192.168.1.107": {"in_traffic": 676, "out_traffic": 408, "threats": 1, "last_seen": "2026-04-27T04:29:32.697195", "is_blocked": false}, "192.168.1.95": {"in_traffic": 533, "out_traffic": 297, "threats": 1, "last_seen": "2026-04-27T04:29:04.757765", "is_blocked": false}, "192.168.1.56": {"in_traffic": 756, "out_traffic": 402, "threats": 0, "last_seen": "2026-04-27T04:29:16.163115", "is_blocked": false}, "192.168.1.196": {"in_traffic": 572, "out_traffic": 203, "threats": 2, "last_seen": "2026-04-27T04:29:30.621509", "is_blocked": false}, "192.168.1.142": {"in_traffic": 501, "out_traffic": 280, "threats": 0, "last_seen": "2026-04-27T04:28:19.633285", "is_blocked": false}, "192.168.1.169": {"in_traffic": 709, "out_traffic": 416, "threats": 1, "last_seen": "2026-04-27T04:26:35.450049", "is_blocked": false}, "192.168.1.40": {"in_traffic": 314, "out_traffic": 222, "threats": 0, "last_seen": "2026-04-27T04:28:14.230315", "is_blocked": false}, "192.168.1.235": {"in_traffic": 387, "out_traffic": 189, "threats": 0, "last_seen": "2026-04-27T04:29:14.062754", "is_blocked": false}, "192.168.1.30": {"in_traffic": 570, "out_traffic": 203, "threats": 1, "last_seen": "2026-04-27T04:29:16.163115", "is_blocked": false}, "192.168.1.23": {"in_traffic": 649, "out_traffic": 377, "threats": 2, "last_seen": "2026-04-27T04:29:33.733107", "is_blocked": false}, "192.168.1.184": {"in_traffic": 495, "out_traffic": 258, "threats": 0, "last_seen": "2026-04-27T04:29:29.588748", "is_blocked": false}, "192.168.1.193": {"in_traffic": 374, "out_traffic": 313, "threats": 1, "last_seen": "2026-04-27T04:28:47.671687", "is_blocked": false}, "192.168.1.161": {"in_traffic": 329, "out_traffic": 207, "threats": 0, "last_seen": "2026-04-27T04:29:22.276573", "is_blocked": false}, "192.168.1.87": {"in_traffic": 229, "out_traffic": 165, "threats": 1, "last_seen": "2026-04-27T04:28:18.591602", "is_blocked": false}, "192.168.1.70": {"in_traffic": 648, "out_traffic": 341, "threats": 1, "last_seen": "2026-04-27T04:29:17.643305", "is_blocked": false}, "192.168.1.130": {"in_traffic": 493, "out_traffic": 162, "threats": 2, "last_seen": "2026-04-27T04:27:47.799816", "is_blocked": false}, "192.168.1.249": {"in_traffic": 616, "out_traffic": 446, "threats": 1, "last_seen": "2026-04-27T04:28:59.461005", "is_blocked": false}, "192.168.1.248": {"in_traffic": 733, "out_traffic": 330, "threats": 0, "last_seen": "2026-04-27T04:29:19.502403", "is_blocked": false}, "192.168.1.26": {"in_traffic": 1013, "out_traffic": 611, "threats": 1, "last_seen": "2026-04-27T04:27:23.795646", "is_blocked": false}, "192.168.1.146": {"in_traffic": 470, "out_traffic": 287, "threats": 0, "last_seen": "2026-04-27T04:28:28.085065", "is_blocked": false}, "192.168.1.90": {"in_traffic": 373, "out_traffic": 253, "threats": 0, "last_seen": "2026-04-27T04:28:09.749908", "is_blocked": false}, "192.168.1.50": {"in_traffic": 692, "out_traffic": 285, "threats": 0, "last_seen": "2026-04-27T04:26:31.302419", "is_blocked": false}, "192.168.1.69": {"in_traffic": 347, "out_traffic": 183, "threats": 2, "last_seen": "2026-04-27T04:27:33.150956", "is_blocked": false}, "192.168.1.38": {"in_traffic": 931, "out_traffic": 484, "threats": 0, "last_seen": "2026-04-27T04:29:26.375162", "is_blocked": false}, "192.168.1.25": {"in_traffic": 809, "out_traffic": 364, "threats": 1, "last_seen": "2026-04-27T04:29:03.646655", "is_blocked": false}, "192.168.1.186": {"in_traffic": 978, "out_traffic": 338, "threats": 2, "last_seen": "2026-04-27T04:28:49.753557", "is_blocked": false}, "192.168.1.31": {"in_traffic": 574, "out_traffic": 247, "threats": 0, "last_seen": "2026-04-27T04:25:36.778944", "is_blocked": false}, "192.168.1.74": {"in_traffic": 778, "out_traffic": 365, "threats": 1, "last_seen": "2026-04-27T04:29:25.055231", "is_blocked": false}, "192.168.1.68": {"in_traffic": 738, "out_traffic": 331, "threats": 0, "last_seen": "2026-04-27T04:29:09.670764", "is_blocked": false}, "192.168.1.125": {"in_traffic": 612, "out_traffic": 352, "threats": 1, "last_seen": "2026-04-27T04:28:57.380050", "is_blocked": false}, "192.168.1.159": {"in_traffic": 532, "out_traffic": 316, "threats": 0, "last_seen": "2026-04-27T04:29:10.736348", "is_blocked": false}, "192.168.1.243": {"in_traffic": 376, "out_traffic": 238, "threats": 0, "last_seen": "2026-04-27T04:27:51.062137", "is_blocked": false}, "192.168.1.123": {"in_traffic": 748, "out_traffic": 245, "threats": 0, "last_seen": "2026-04-27T04:28:45.380637", "is_blocked": false}, "192.168.1.240": {"in_traffic": 501, "out_traffic": 372, "threats": 2, "last_seen": "2026-04-27T04:29:11.796975", "is_blocked": false}, "192.168.1.138": {"in_traffic": 735, "out_traffic": 330, "threats": 3, "last_seen": "2026-04-27T04:27:02.713144", "is_blocked": false}, "192.168.1.250": {"in_traffic": 580, "out_traffic": 273, "threats": 0, "last_seen": "2026-04-27T04:26:38.551630", "is_blocked": false}, "192.168.1.219": {"in_traffic": 487, "out_traffic": 257, "threats": 0, "last_seen": "2026-04-27T04:29:23.454369", "is_blocked": false}, "192.168.1.145": {"in_traffic": 854, "out_traffic": 239, "threats": 2, "last_seen": "2026-04-27T04:29:14.062754", "is_blocked": false}, "192.168.1.97": {"in_traffic": 739, "out_traffic": 357, "threats": 0, "last_seen": "2026-04-27T04:29:07.529680", "is_blocked": false}, "192.168.1.82": {"in_traffic": 718, "out_traffic": 310, "threats": 0, "last_seen": "2026-04-27T04:28:51.930972", "is_blocked": false}, "192.168.1.102": {"in_traffic": 583, "out_traffic": 208, "threats": 0, "last_seen": "2026-04-27T04:29:19.502403", "is_blocked": false}, "192.168.1.35": {"in_traffic": 730, "out_traffic": 428, "threats": 0, "last_seen": "2026-04-27T04:29:16.163115", "is_blocked": false}, "192.168.1.5": {"in_traffic": 599, "out_traffic": 239, "threats": 0, "last_seen": "2026-04-27T04:29:03.646655", "is_blocked": false}}}