{"timestamp": "2025-12-01T10:36:42.291745", "traffic_in": 1083392, "traffic_out": 722944, "connections": 76, "packets_processed": 332, "threats_detected": 5, "ips_blocked": 0, "protocol_stats": {"TCP": 28, "UDP": 61, "HTTP": 34, "HTTPS": 30, "ICMP": 33, "DNS": 59, "Other": 48}, "attack_stats": {"SQL\u6ce8\u5165": 1, "XSS\u653b\u51fb": 0, "DDoS\u653b\u51fb": 1, "\u7aef\u53e3\u626b\u63cf": 1, "\u66b4\u529b\u7834\u89e3": 0, "\u5f02\u5e38\u6d41\u91cf": 2, "\u75c5\u6bd2/\u6728\u9a6c": 0}, "ip_data": {"192.168.1.66": {"in_traffic": 308, "out_traffic": 119, "threats": 0, "last_seen": "2025-12-01T10:36:42.291745", "is_blocked": false}, "192.168.1.114": {"in_traffic": 133, "out_traffic": 61, "threats": 0, "last_seen": "2025-12-01T10:36:41.284888", "is_blocked": false}, "192.168.1.150": {"in_traffic": 124, "out_traffic": 47, "threats": 0, "last_seen": "2025-12-01T10:36:31.215589", "is_blocked": false}, "192.168.1.10": {"in_traffic": 116, "out_traffic": 52, "threats": 0, "last_seen": "2025-12-01T10:36:33.236237", "is_blocked": false}, "192.168.1.236": {"in_traffic": 98, "out_traffic": 57, "threats": 0, "last_seen": "2025-12-01T10:36:36.257165", "is_blocked": false}}}