{"timestamp": "2026-04-26T22:54:34.934003", "traffic_in": 713728, "traffic_out": 55296, "connections": 33, "packets_processed": 947, "threats_detected": 16, "ips_blocked": 0, "protocol_stats": {"TCP": 51, "UDP": 93, "HTTP": 68, "HTTPS": 65, "ICMP": 89, "DNS": 136, "Other": 58}, "attack_stats": {"SQL\u6ce8\u5165": 4, "XSS\u653b\u51fb": 3, "DDoS\u653b\u51fb": 2, "\u7aef\u53e3\u626b\u63cf": 3, "\u66b4\u529b\u7834\u89e3": 1, "\u5f02\u5e38\u6d41\u91cf": 1, "\u75c5\u6bd2/\u6728\u9a6c": 2}, "ip_data": {"192.168.1.153": {"in_traffic": 172, "out_traffic": 123, "threats": 0, "last_seen": "2026-04-26T22:54:33.925259", "is_blocked": false}, "192.168.1.71": {"in_traffic": 208, "out_traffic": 82, "threats": 0, "last_seen": "2026-04-26T22:54:33.925259", "is_blocked": false}, "192.168.1.181": {"in_traffic": 206, "out_traffic": 67, "threats": 0, "last_seen": "2026-04-26T22:54:23.813024", "is_blocked": false}, "192.168.1.229": {"in_traffic": 187, "out_traffic": 78, "threats": 0, "last_seen": "2026-04-26T22:54:22.804339", "is_blocked": false}, "192.168.1.135": {"in_traffic": 179, "out_traffic": 58, "threats": 0, "last_seen": "2026-04-26T22:54:32.903180", "is_blocked": false}}}