{"traffic_history": [{"timestamp": "2026-05-23T10:05:33.670421", "incoming": 1301, "outgoing": 734}, {"timestamp": "2026-05-23T10:05:34.671844", "incoming": 985, "outgoing": 726}, {"timestamp": "2026-05-23T10:05:35.680295", "incoming": 344, "outgoing": 511}, {"timestamp": "2026-05-23T10:05:36.690161", "incoming": 104, "outgoing": 152}, {"timestamp": "2026-05-23T10:05:37.701773", "incoming": 1109, "outgoing": 325}, {"timestamp": "2026-05-23T10:05:38.743345", "incoming": 870, "outgoing": 752}, {"timestamp": "2026-05-23T10:05:39.778360", "incoming": 623, "outgoing": 125}, {"timestamp": "2026-05-23T10:05:40.785788", "incoming": 819, "outgoing": 695}, {"timestamp": "2026-05-23T10:05:41.802350", "incoming": 1193, "outgoing": 76}, {"timestamp": "2026-05-23T10:05:42.822660", "incoming": 1344, "outgoing": 531}, {"timestamp": "2026-05-23T10:05:43.837704", "incoming": 1081, "outgoing": 425}, {"timestamp": "2026-05-23T10:05:44.856462", "incoming": 1418, "outgoing": 737}, {"timestamp": "2026-05-23T10:05:45.867600", "incoming": 1222, "outgoing": 255}, {"timestamp": "2026-05-23T10:05:46.880983", "incoming": 795, "outgoing": 613}, {"timestamp": "2026-05-23T10:05:47.889537", "incoming": 132, "outgoing": 371}, {"timestamp": "2026-05-23T10:05:48.901520", "incoming": 781, "outgoing": 619}, {"timestamp": "2026-05-23T10:05:49.914086", "incoming": 1286, "outgoing": 737}, {"timestamp": "2026-05-23T10:05:50.928817", "incoming": 792, "outgoing": 570}, {"timestamp": "2026-05-23T10:05:51.940891", "incoming": 806, "outgoing": 59}, {"timestamp": "2026-05-23T10:05:52.955936", "incoming": 415, "outgoing": 523}, {"timestamp": "2026-05-23T10:05:53.967887", "incoming": 1473, "outgoing": 368}, {"timestamp": "2026-05-23T10:05:54.990290", "incoming": 854, "outgoing": 686}, {"timestamp": "2026-05-23T10:05:55.999382", "incoming": 1159, "outgoing": 297}, {"timestamp": "2026-05-23T10:05:57.010890", "incoming": 738, "outgoing": 495}, {"timestamp": "2026-05-23T10:05:58.029753", "incoming": 1341, "outgoing": 573}, {"timestamp": "2026-05-23T10:05:59.043111", "incoming": 456, "outgoing": 649}, {"timestamp": "2026-05-23T10:06:00.056078", "incoming": 158, "outgoing": 341}, {"timestamp": "2026-05-23T10:06:01.069666", "incoming": 941, "outgoing": 685}, {"timestamp": "2026-05-23T10:06:02.081317", "incoming": 407, "outgoing": 518}, {"timestamp": "2026-05-23T10:06:03.094700", "incoming": 789, "outgoing": 756}, {"timestamp": "2026-05-23T10:06:04.111440", "incoming": 472, "outgoing": 501}, {"timestamp": "2026-05-23T10:06:05.144463", "incoming": 142, "outgoing": 739}, {"timestamp": "2026-05-23T10:06:06.161179", "incoming": 749, "outgoing": 522}, {"timestamp": "2026-05-23T10:06:07.179786", "incoming": 694, "outgoing": 415}, {"timestamp": "2026-05-23T10:06:08.193983", "incoming": 320, "outgoing": 770}, {"timestamp": "2026-05-23T10:06:09.213670", "incoming": 1025, "outgoing": 603}, {"timestamp": "2026-05-23T10:06:10.227504", "incoming": 1150, "outgoing": 380}, {"timestamp": "2026-05-23T10:06:11.244003", "incoming": 372, "outgoing": 716}, {"timestamp": "2026-05-23T10:06:12.257606", "incoming": 886, "outgoing": 138}, {"timestamp": "2026-05-23T10:06:13.268990", "incoming": 892, "outgoing": 436}, {"timestamp": "2026-05-23T10:06:14.285321", "incoming": 750, "outgoing": 632}, {"timestamp": "2026-05-23T10:06:15.295347", "incoming": 1032, "outgoing": 763}, {"timestamp": "2026-05-23T10:06:16.309564", "incoming": 1316, "outgoing": 66}, {"timestamp": "2026-05-23T10:06:17.324553", "incoming": 951, "outgoing": 93}, {"timestamp": "2026-05-23T10:06:18.335954", "incoming": 372, "outgoing": 678}, {"timestamp": "2026-05-23T10:06:19.345383", "incoming": 751, "outgoing": 143}, {"timestamp": "2026-05-23T10:06:20.356709", "incoming": 258, "outgoing": 197}, {"timestamp": "2026-05-23T10:06:21.369555", "incoming": 1031, "outgoing": 167}, {"timestamp": "2026-05-23T10:06:22.403368", "incoming": 628, "outgoing": 634}, {"timestamp": "2026-05-23T10:06:23.415215", "incoming": 459, "outgoing": 480}, {"timestamp": "2026-05-23T10:06:24.442009", "incoming": 256, "outgoing": 465}, {"timestamp": "2026-05-23T10:06:25.485093", "incoming": 166, "outgoing": 619}, {"timestamp": "2026-05-23T10:06:26.497644", "incoming": 1020, "outgoing": 536}, {"timestamp": "2026-05-23T10:06:27.509415", "incoming": 871, "outgoing": 569}, {"timestamp": "2026-05-23T10:06:28.528757", "incoming": 919, "outgoing": 76}, {"timestamp": "2026-05-23T10:06:29.544385", "incoming": 730, "outgoing": 419}, {"timestamp": "2026-05-23T10:06:30.556488", "incoming": 1387, "outgoing": 280}, {"timestamp": "2026-05-23T10:06:31.574560", "incoming": 1375, "outgoing": 266}, {"timestamp": "2026-05-23T10:06:32.594151", "incoming": 344, "outgoing": 486}, {"timestamp": "2026-05-23T10:06:33.609549", "incoming": 232, "outgoing": 346}, {"timestamp": "2026-05-23T10:06:34.650450", "incoming": 833, "outgoing": 369}, {"timestamp": "2026-05-23T10:06:35.691499", "incoming": 1200, "outgoing": 448}, {"timestamp": "2026-05-23T10:06:36.726372", "incoming": 721, "outgoing": 211}, {"timestamp": "2026-05-23T10:06:37.765075", "incoming": 1359, "outgoing": 259}, {"timestamp": "2026-05-23T10:06:38.799181", "incoming": 800, "outgoing": 357}, {"timestamp": "2026-05-23T10:06:39.828399", "incoming": 290, "outgoing": 274}, {"timestamp": "2026-05-23T10:06:40.869008", "incoming": 779, "outgoing": 425}, {"timestamp": "2026-05-23T10:06:41.904487", "incoming": 477, "outgoing": 301}, {"timestamp": "2026-05-23T10:06:42.931280", "incoming": 475, "outgoing": 579}, {"timestamp": "2026-05-23T10:06:43.965733", "incoming": 561, "outgoing": 241}, {"timestamp": "2026-05-23T10:06:45.006987", "incoming": 1115, "outgoing": 475}, {"timestamp": "2026-05-23T10:06:46.043821", "incoming": 1316, "outgoing": 231}, {"timestamp": "2026-05-23T10:06:47.085345", "incoming": 1031, "outgoing": 484}, {"timestamp": "2026-05-23T10:06:48.121711", "incoming": 926, "outgoing": 498}, {"timestamp": "2026-05-23T10:06:49.153291", "incoming": 467, "outgoing": 597}, {"timestamp": "2026-05-23T10:06:50.189627", "incoming": 655, "outgoing": 418}, {"timestamp": "2026-05-23T10:06:51.224256", "incoming": 396, "outgoing": 152}, {"timestamp": "2026-05-23T10:06:52.267754", "incoming": 443, "outgoing": 674}, {"timestamp": "2026-05-23T10:06:53.299885", "incoming": 186, "outgoing": 489}, {"timestamp": "2026-05-23T10:06:54.333799", "incoming": 731, "outgoing": 770}, {"timestamp": "2026-05-23T10:06:55.360584", "incoming": 1322, "outgoing": 240}, {"timestamp": "2026-05-23T10:06:56.385626", "incoming": 166, "outgoing": 79}, {"timestamp": "2026-05-23T10:06:57.420291", "incoming": 532, "outgoing": 653}, {"timestamp": "2026-05-23T10:06:58.448449", "incoming": 514, "outgoing": 75}, {"timestamp": "2026-05-23T10:06:59.487650", "incoming": 190, "outgoing": 709}, {"timestamp": "2026-05-23T10:07:00.528185", "incoming": 1338, "outgoing": 569}, {"timestamp": "2026-05-23T10:07:01.553124", "incoming": 928, "outgoing": 376}, {"timestamp": "2026-05-23T10:07:02.602766", "incoming": 1324, "outgoing": 86}, {"timestamp": "2026-05-23T10:07:03.648176", "incoming": 233, "outgoing": 605}, {"timestamp": "2026-05-23T10:07:04.714868", "incoming": 755, "outgoing": 59}, {"timestamp": "2026-05-23T10:07:05.766398", "incoming": 1097, "outgoing": 572}, {"timestamp": "2026-05-23T10:07:06.804155", "incoming": 1328, "outgoing": 261}, {"timestamp": "2026-05-23T10:07:07.859084", "incoming": 379, "outgoing": 343}, {"timestamp": "2026-05-23T10:07:08.922412", "incoming": 856, "outgoing": 708}, {"timestamp": "2026-05-23T10:07:09.958174", "incoming": 837, "outgoing": 71}, {"timestamp": "2026-05-23T10:07:11.084688", "incoming": 845, "outgoing": 111}, {"timestamp": "2026-05-23T10:07:12.192141", "incoming": 1089, "outgoing": 667}, {"timestamp": "2026-05-23T10:07:13.225625", "incoming": 157, "outgoing": 316}, {"timestamp": "2026-05-23T10:07:14.255735", "incoming": 602, "outgoing": 552}, {"timestamp": "2026-05-23T10:07:15.301565", "incoming": 813, "outgoing": 231}, {"timestamp": "2026-05-23T10:07:16.336415", "incoming": 844, "outgoing": 62}, {"timestamp": "2026-05-23T10:07:17.389090", "incoming": 1452, "outgoing": 659}, {"timestamp": "2026-05-23T10:07:18.425622", "incoming": 995, "outgoing": 612}, {"timestamp": "2026-05-23T10:07:19.460141", "incoming": 1279, "outgoing": 76}, {"timestamp": "2026-05-23T10:07:20.489925", "incoming": 438, "outgoing": 550}, {"timestamp": "2026-05-23T10:07:21.514434", "incoming": 1368, "outgoing": 233}, {"timestamp": "2026-05-23T10:07:22.539967", "incoming": 591, "outgoing": 360}, {"timestamp": "2026-05-23T10:07:23.565674", "incoming": 908, "outgoing": 281}, {"timestamp": "2026-05-23T10:08:02.549723", "incoming": 1491, "outgoing": 303}, {"timestamp": "2026-05-23T10:08:03.572508", "incoming": 1418, "outgoing": 463}, {"timestamp": "2026-05-23T10:08:04.596794", "incoming": 1165, "outgoing": 604}, {"timestamp": "2026-05-23T10:08:05.701069", "incoming": 219, "outgoing": 779}, {"timestamp": "2026-05-23T10:08:06.751193", "incoming": 1390, "outgoing": 235}, {"timestamp": "2026-05-23T10:08:07.775254", "incoming": 1016, "outgoing": 582}, {"timestamp": "2026-05-23T10:08:08.801386", "incoming": 534, "outgoing": 381}, {"timestamp": "2026-05-23T10:08:09.837812", "incoming": 633, "outgoing": 289}, {"timestamp": "2026-05-23T10:08:10.869340", "incoming": 433, "outgoing": 212}, {"timestamp": "2026-05-23T10:08:11.900520", "incoming": 472, "outgoing": 229}, {"timestamp": "2026-05-23T10:08:12.925996", "incoming": 927, "outgoing": 227}, {"timestamp": "2026-05-23T10:08:13.962420", "incoming": 239, "outgoing": 110}, {"timestamp": "2026-05-23T10:08:14.994584", "incoming": 619, "outgoing": 664}, {"timestamp": "2026-05-23T10:08:16.016485", "incoming": 400, "outgoing": 82}, {"timestamp": "2026-05-23T10:08:17.059626", "incoming": 1015, "outgoing": 702}, {"timestamp": "2026-05-23T10:08:18.085201", "incoming": 1298, "outgoing": 242}, {"timestamp": "2026-05-23T10:08:19.106688", "incoming": 503, "outgoing": 563}, {"timestamp": "2026-05-23T10:08:20.160443", "incoming": 1378, "outgoing": 232}, {"timestamp": "2026-05-23T10:08:21.189667", "incoming": 1207, "outgoing": 622}, {"timestamp": "2026-05-23T10:08:22.215221", "incoming": 1242, "outgoing": 383}, {"timestamp": "2026-05-23T10:08:23.239391", "incoming": 1213, "outgoing": 289}, {"timestamp": "2026-05-23T10:08:24.295095", "incoming": 1131, "outgoing": 242}, {"timestamp": "2026-05-23T10:08:25.330030", "incoming": 961, "outgoing": 735}, {"timestamp": "2026-05-23T10:08:26.371795", "incoming": 1251, "outgoing": 384}, {"timestamp": "2026-05-23T10:08:27.448195", "incoming": 475, "outgoing": 116}, {"timestamp": "2026-05-23T10:08:28.472441", "incoming": 864, "outgoing": 294}, {"timestamp": "2026-05-23T10:08:29.512818", "incoming": 483, "outgoing": 695}, {"timestamp": "2026-05-23T10:08:30.536790", "incoming": 123, "outgoing": 644}, {"timestamp": "2026-05-23T10:08:31.579100", "incoming": 978, "outgoing": 550}, {"timestamp": "2026-05-23T10:08:32.604414", "incoming": 611, "outgoing": 277}, {"timestamp": "2026-05-23T10:08:33.650358", "incoming": 1298, "outgoing": 84}, {"timestamp": "2026-05-23T10:08:34.683693", "incoming": 1288, "outgoing": 367}, {"timestamp": "2026-05-23T10:08:35.732185", "incoming": 575, "outgoing": 553}, {"timestamp": "2026-05-23T10:08:36.777579", "incoming": 142, "outgoing": 490}, {"timestamp": "2026-05-23T10:08:37.832866", "incoming": 1368, "outgoing": 681}, {"timestamp": "2026-05-23T10:08:38.868452", "incoming": 698, "outgoing": 63}, {"timestamp": "2026-05-23T10:08:39.894331", "incoming": 450, "outgoing": 64}, {"timestamp": "2026-05-23T10:08:40.921214", "incoming": 1117, "outgoing": 236}, {"timestamp": "2026-05-23T10:08:41.973828", "incoming": 867, "outgoing": 700}, {"timestamp": "2026-05-23T10:08:43.023777", "incoming": 573, "outgoing": 555}, {"timestamp": "2026-05-23T10:08:44.081650", "incoming": 1074, "outgoing": 113}, {"timestamp": "2026-05-23T10:08:45.124341", "incoming": 415, "outgoing": 783}, {"timestamp": "2026-05-23T10:08:46.173285", "incoming": 725, "outgoing": 504}, {"timestamp": "2026-05-23T10:08:47.214979", "incoming": 1385, "outgoing": 248}, {"timestamp": "2026-05-23T10:08:48.263833", "incoming": 1254, "outgoing": 384}, {"timestamp": "2026-05-23T10:08:49.344449", "incoming": 732, "outgoing": 569}, {"timestamp": "2026-05-23T10:08:50.389082", "incoming": 570, "outgoing": 231}, {"timestamp": "2026-05-23T10:08:51.441014", "incoming": 587, "outgoing": 772}, {"timestamp": "2026-05-23T10:08:52.478685", "incoming": 168, "outgoing": 189}, {"timestamp": "2026-05-23T10:08:53.523436", "incoming": 782, "outgoing": 770}, {"timestamp": "2026-05-23T10:08:54.571175", "incoming": 1361, "outgoing": 168}, {"timestamp": "2026-05-23T10:08:55.596001", "incoming": 631, "outgoing": 686}, {"timestamp": "2026-05-23T10:08:56.635407", "incoming": 226, "outgoing": 642}, {"timestamp": "2026-05-23T10:08:57.663079", "incoming": 1036, "outgoing": 709}, {"timestamp": "2026-05-23T10:08:58.692431", "incoming": 1123, "outgoing": 69}, {"timestamp": "2026-05-23T10:08:59.744983", "incoming": 737, "outgoing": 351}, {"timestamp": "2026-05-23T10:09:00.778498", "incoming": 133, "outgoing": 109}, {"timestamp": "2026-05-23T10:09:01.804352", "incoming": 1290, "outgoing": 517}, {"timestamp": "2026-05-23T10:09:02.833403", "incoming": 570, "outgoing": 635}, {"timestamp": "2026-05-23T10:09:03.859665", "incoming": 101, "outgoing": 446}, {"timestamp": "2026-05-23T10:09:04.885869", "incoming": 889, "outgoing": 760}, {"timestamp": "2026-05-23T10:09:05.930334", "incoming": 964, "outgoing": 774}, {"timestamp": "2026-05-23T10:09:06.980485", "incoming": 1189, "outgoing": 285}, {"timestamp": "2026-05-23T10:09:08.020543", "incoming": 109, "outgoing": 347}, {"timestamp": "2026-05-23T10:09:09.090767", "incoming": 1157, "outgoing": 633}, {"timestamp": "2026-05-23T10:09:10.119455", "incoming": 558, "outgoing": 272}, {"timestamp": "2026-05-23T10:09:11.140674", "incoming": 1166, "outgoing": 770}, {"timestamp": "2026-05-23T10:09:12.174307", "incoming": 202, "outgoing": 373}, {"timestamp": "2026-05-23T10:09:13.235950", "incoming": 464, "outgoing": 55}, {"timestamp": "2026-05-23T10:09:14.263561", "incoming": 1267, "outgoing": 740}, {"timestamp": "2026-05-23T10:09:15.304822", "incoming": 490, "outgoing": 431}, {"timestamp": "2026-05-23T10:09:16.362124", "incoming": 1119, "outgoing": 521}, {"timestamp": "2026-05-23T10:09:17.482532", "incoming": 1266, "outgoing": 663}, {"timestamp": "2026-05-23T10:09:18.545329", "incoming": 1167, "outgoing": 436}, {"timestamp": "2026-05-23T10:09:19.588996", "incoming": 385, "outgoing": 424}, {"timestamp": "2026-05-23T10:09:20.649707", "incoming": 1101, "outgoing": 545}, {"timestamp": "2026-05-23T10:09:21.692327", "incoming": 284, "outgoing": 348}, {"timestamp": "2026-05-23T10:09:22.755973", "incoming": 865, "outgoing": 226}, {"timestamp": "2026-05-23T10:09:23.810730", "incoming": 1056, "outgoing": 233}, {"timestamp": "2026-05-23T10:09:24.871389", "incoming": 968, "outgoing": 192}, {"timestamp": "2026-05-23T10:09:25.907445", "incoming": 675, "outgoing": 707}, {"timestamp": "2026-05-23T10:09:26.945433", "incoming": 124, "outgoing": 757}, {"timestamp": "2026-05-23T10:09:28.029655", "incoming": 1227, "outgoing": 429}, {"timestamp": "2026-05-23T10:09:29.097628", "incoming": 1472, "outgoing": 205}, {"timestamp": "2026-05-23T10:09:30.244289", "incoming": 1003, "outgoing": 429}, {"timestamp": "2026-05-23T10:09:31.305636", "incoming": 1371, "outgoing": 658}, {"timestamp": "2026-05-23T10:09:32.352551", "incoming": 1479, "outgoing": 457}, {"timestamp": "2026-05-23T10:09:33.408473", "incoming": 103, "outgoing": 748}, {"timestamp": "2026-05-23T10:09:34.446031", "incoming": 322, "outgoing": 131}, {"timestamp": "2026-05-23T10:09:35.486107", "incoming": 1408, "outgoing": 619}, {"timestamp": "2026-05-23T10:09:36.541530", "incoming": 1276, "outgoing": 251}, {"timestamp": "2026-05-23T10:09:37.591822", "incoming": 1157, "outgoing": 156}, {"timestamp": "2026-05-23T10:09:38.630413", "incoming": 717, "outgoing": 548}, {"timestamp": "2026-05-23T10:09:39.677610", "incoming": 837, "outgoing": 367}, {"timestamp": "2026-05-23T10:09:40.710588", "incoming": 1302, "outgoing": 149}, {"timestamp": "2026-05-23T10:09:41.744739", "incoming": 738, "outgoing": 152}, {"timestamp": "2026-05-23T10:09:42.766113", "incoming": 1137, "outgoing": 53}, {"timestamp": "2026-05-23T10:09:43.798863", "incoming": 245, "outgoing": 238}, {"timestamp": "2026-05-23T10:09:44.841520", "incoming": 874, "outgoing": 576}, {"timestamp": "2026-05-23T10:09:45.870335", "incoming": 725, "outgoing": 662}, {"timestamp": "2026-05-23T10:09:46.892875", "incoming": 976, "outgoing": 793}, {"timestamp": "2026-05-23T10:09:47.928332", "incoming": 863, "outgoing": 427}, {"timestamp": "2026-05-23T10:09:48.953276", "incoming": 1241, "outgoing": 503}, {"timestamp": "2026-05-23T10:09:49.980718", "incoming": 115, "outgoing": 636}, {"timestamp": "2026-05-23T10:09:51.009352", "incoming": 613, "outgoing": 168}, {"timestamp": "2026-05-23T10:09:52.039364", "incoming": 705, "outgoing": 421}, {"timestamp": "2026-05-23T10:09:53.088731", "incoming": 1094, "outgoing": 703}, {"timestamp": "2026-05-23T10:09:54.122642", "incoming": 126, "outgoing": 371}, {"timestamp": "2026-05-23T10:09:55.150342", "incoming": 424, "outgoing": 687}, {"timestamp": "2026-05-23T10:09:56.192801", "incoming": 1012, "outgoing": 393}, {"timestamp": "2026-05-23T10:09:57.217706", "incoming": 215, "outgoing": 530}, {"timestamp": "2026-05-23T10:09:58.250024", "incoming": 1480, "outgoing": 386}, {"timestamp": "2026-05-23T10:09:59.276708", "incoming": 882, "outgoing": 517}, {"timestamp": "2026-05-23T10:10:00.305290", "incoming": 1145, "outgoing": 718}, {"timestamp": "2026-05-23T10:10:01.326940", "incoming": 836, "outgoing": 432}, {"timestamp": "2026-05-23T10:10:02.375654", "incoming": 1199, "outgoing": 399}, {"timestamp": "2026-05-23T10:10:03.406232", "incoming": 1087, "outgoing": 271}, {"timestamp": "2026-05-23T10:10:04.427500", "incoming": 137, "outgoing": 478}, {"timestamp": "2026-05-23T10:10:05.448191", "incoming": 1277, "outgoing": 523}, {"timestamp": "2026-05-23T10:10:06.483660", "incoming": 1025, "outgoing": 185}, {"timestamp": "2026-05-23T10:10:07.504141", "incoming": 1388, "outgoing": 70}, {"timestamp": "2026-05-23T10:10:08.528063", "incoming": 310, "outgoing": 256}, {"timestamp": "2026-05-23T10:10:09.551026", "incoming": 1014, "outgoing": 180}, {"timestamp": "2026-05-23T10:10:10.581249", "incoming": 1218, "outgoing": 255}, {"timestamp": "2026-05-23T10:10:11.606908", "incoming": 1234, "outgoing": 598}, {"timestamp": "2026-05-23T10:10:12.629772", "incoming": 1046, "outgoing": 603}, {"timestamp": "2026-05-23T10:10:13.650682", "incoming": 374, "outgoing": 467}, {"timestamp": "2026-05-23T10:10:14.677310", "incoming": 864, "outgoing": 439}, {"timestamp": "2026-05-23T10:10:15.704265", "incoming": 1316, "outgoing": 77}, {"timestamp": "2026-05-23T10:10:16.737430", "incoming": 1011, "outgoing": 65}, {"timestamp": "2026-05-23T10:10:17.760156", "incoming": 228, "outgoing": 480}, {"timestamp": "2026-05-23T10:10:18.781983", "incoming": 977, "outgoing": 154}, {"timestamp": "2026-05-23T10:10:19.833739", "incoming": 1493, "outgoing": 452}, {"timestamp": "2026-05-23T10:10:20.901008", "incoming": 1118, "outgoing": 657}, {"timestamp": "2026-05-23T10:10:21.943352", "incoming": 1423, "outgoing": 612}, {"timestamp": "2026-05-23T10:10:22.971033", "incoming": 406, "outgoing": 80}, {"timestamp": "2026-05-23T10:10:24.021641", "incoming": 148, "outgoing": 101}, {"timestamp": "2026-05-23T10:10:25.087544", "incoming": 651, "outgoing": 278}, {"timestamp": "2026-05-23T10:10:26.132375", "incoming": 1448, "outgoing": 559}, {"timestamp": "2026-05-23T10:10:27.171358", "incoming": 310, "outgoing": 582}, {"timestamp": "2026-05-23T10:10:28.220778", "incoming": 593, "outgoing": 726}, {"timestamp": "2026-05-23T10:10:29.278029", "incoming": 411, "outgoing": 62}, {"timestamp": "2026-05-23T10:10:30.335436", "incoming": 1394, "outgoing": 634}, {"timestamp": "2026-05-23T10:10:31.375122", "incoming": 994, "outgoing": 609}, {"timestamp": "2026-05-23T10:10:32.412556", "incoming": 207, "outgoing": 302}, {"timestamp": "2026-05-23T10:10:33.490979", "incoming": 303, "outgoing": 787}, {"timestamp": "2026-05-23T10:10:34.533022", "incoming": 1035, "outgoing": 111}, {"timestamp": "2026-05-23T10:10:35.588510", "incoming": 1215, "outgoing": 628}, {"timestamp": "2026-05-23T10:10:36.636371", "incoming": 1015, "outgoing": 793}, {"timestamp": "2026-05-23T10:10:37.701349", "incoming": 1155, "outgoing": 580}, {"timestamp": "2026-05-23T10:10:38.752475", "incoming": 816, "outgoing": 177}, {"timestamp": "2026-05-23T10:10:39.796790", "incoming": 533, "outgoing": 650}, {"timestamp": "2026-05-23T10:10:40.847436", "incoming": 1485, "outgoing": 333}, {"timestamp": "2026-05-23T10:10:41.904833", "incoming": 789, "outgoing": 499}, {"timestamp": "2026-05-23T10:10:42.964257", "incoming": 288, "outgoing": 411}, {"timestamp": "2026-05-23T10:10:43.999991", "incoming": 730, "outgoing": 173}, {"timestamp": "2026-05-23T10:10:45.034293", "incoming": 1412, "outgoing": 642}, {"timestamp": "2026-05-23T10:10:46.064803", "incoming": 1386, "outgoing": 84}, {"timestamp": "2026-05-23T10:10:47.090813", "incoming": 977, "outgoing": 681}, {"timestamp": "2026-05-23T10:10:48.136898", "incoming": 929, "outgoing": 104}, {"timestamp": "2026-05-23T10:10:49.190292", "incoming": 761, "outgoing": 745}, {"timestamp": "2026-05-23T10:10:50.246298", "incoming": 1301, "outgoing": 253}, {"timestamp": "2026-05-23T10:10:51.309193", "incoming": 1477, "outgoing": 342}, {"timestamp": "2026-05-23T10:10:52.380726", "incoming": 859, "outgoing": 328}, {"timestamp": "2026-05-23T10:10:53.404005", "incoming": 1306, "outgoing": 157}, {"timestamp": "2026-05-23T10:10:54.426398", "incoming": 473, "outgoing": 100}, {"timestamp": "2026-05-23T10:10:55.464228", "incoming": 1169, "outgoing": 356}, {"timestamp": "2026-05-23T10:10:56.486423", "incoming": 745, "outgoing": 626}, {"timestamp": "2026-05-23T10:10:57.516230", "incoming": 1332, "outgoing": 464}, {"timestamp": "2026-05-23T10:10:58.548241", "incoming": 499, "outgoing": 695}, {"timestamp": "2026-05-23T10:10:59.572887", "incoming": 575, "outgoing": 125}, {"timestamp": "2026-05-23T10:11:00.607984", "incoming": 598, "outgoing": 729}, {"timestamp": "2026-05-23T10:11:01.657869", "incoming": 435, "outgoing": 165}, {"timestamp": "2026-05-23T10:11:02.689574", "incoming": 1179, "outgoing": 543}, {"timestamp": "2026-05-23T10:11:03.722153", "incoming": 1184, "outgoing": 536}, {"timestamp": "2026-05-23T10:11:04.755121", "incoming": 677, "outgoing": 200}, {"timestamp": "2026-05-23T10:11:05.776655", "incoming": 554, "outgoing": 565}, {"timestamp": "2026-05-23T10:11:06.800047", "incoming": 196, "outgoing": 543}, {"timestamp": "2026-05-23T10:11:07.827384", "incoming": 652, "outgoing": 517}, {"timestamp": "2026-05-23T10:11:08.854233", "incoming": 1323, "outgoing": 688}, {"timestamp": "2026-05-23T10:11:09.892616", "incoming": 205, "outgoing": 706}, {"timestamp": "2026-05-23T10:11:10.924548", "incoming": 1185, "outgoing": 502}, {"timestamp": "2026-05-23T10:11:11.958547", "incoming": 1346, "outgoing": 715}, {"timestamp": "2026-05-23T10:11:12.988582", "incoming": 624, "outgoing": 560}, {"timestamp": "2026-05-23T10:11:14.051858", "incoming": 850, "outgoing": 108}, {"timestamp": "2026-05-23T10:11:15.077032", "incoming": 434, "outgoing": 452}, {"timestamp": "2026-05-23T10:11:16.108311", "incoming": 1359, "outgoing": 610}, {"timestamp": "2026-05-23T10:11:17.149082", "incoming": 1243, "outgoing": 108}, {"timestamp": "2026-05-23T10:11:18.185931", "incoming": 641, "outgoing": 171}, {"timestamp": "2026-05-23T10:11:19.227174", "incoming": 1028, "outgoing": 220}, {"timestamp": "2026-05-23T10:11:20.251665", "incoming": 936, "outgoing": 588}, {"timestamp": "2026-05-23T10:11:21.285548", "incoming": 789, "outgoing": 380}], "protocol_stats": {"TCP": 771, "UDP": 703, "HTTP": 757, "HTTPS": 727, "ICMP": 532, "DNS": 707, "Other": 757}, "attack_stats": {"SQL\u6ce8\u5165": 13, "XSS\u653b\u51fb": 20, "DDoS\u653b\u51fb": 11, "\u7aef\u53e3\u626b\u63cf": 10, "\u66b4\u529b\u7834\u89e3": 12, "\u5f02\u5e38\u6d41\u91cf": 11, "\u75c5\u6bd2/\u6728\u9a6c": 8}, "ip_data": {"192.168.1.250": {"in_traffic": 72, "out_traffic": 50, "threats": 1, "last_seen": "2026-05-23T10:08:55.596001", "is_blocked": false}, "192.168.1.208": {"in_traffic": 370, "out_traffic": 171, "threats": 1, "last_seen": "2026-05-23T10:11:02.689574", "is_blocked": false}, "192.168.1.36": {"in_traffic": 339, "out_traffic": 168, "threats": 0, "last_seen": "2026-05-23T10:10:27.171358", "is_blocked": false}, "192.168.1.68": {"in_traffic": 494, "out_traffic": 314, "threats": 0, "last_seen": "2026-05-23T10:11:21.285548", "is_blocked": false}, "192.168.1.143": {"in_traffic": 387, "out_traffic": 160, "threats": 0, "last_seen": "2026-05-23T10:07:05.766398", "is_blocked": false}, "192.168.1.118": {"in_traffic": 180, "out_traffic": 113, "threats": 0, "last_seen": "2026-05-23T10:10:22.971033", "is_blocked": false}, "192.168.1.193": {"in_traffic": 514, "out_traffic": 262, "threats": 0, "last_seen": "2026-05-23T10:11:21.285548", "is_blocked": false}, "192.168.1.32": {"in_traffic": 354, "out_traffic": 141, "threats": 0, "last_seen": "2026-05-23T10:10:59.572887", "is_blocked": false}, "192.168.1.161": {"in_traffic": 211, "out_traffic": 70, "threats": 0, "last_seen": "2026-05-23T10:11:15.077032", "is_blocked": false}, "192.168.1.87": {"in_traffic": 378, "out_traffic": 195, "threats": 0, "last_seen": "2026-05-23T10:10:09.551026", "is_blocked": false}, "192.168.1.105": {"in_traffic": 222, "out_traffic": 96, "threats": 1, "last_seen": "2026-05-23T10:10:53.404005", "is_blocked": false}, "192.168.1.38": {"in_traffic": 212, "out_traffic": 156, "threats": 0, "last_seen": "2026-05-23T10:10:38.752475", "is_blocked": false}, "192.168.1.115": {"in_traffic": 358, "out_traffic": 157, "threats": 1, "last_seen": "2026-05-23T10:11:12.988582", "is_blocked": false}, "192.168.1.159": {"in_traffic": 252, "out_traffic": 159, "threats": 0, "last_seen": "2026-05-23T10:10:02.375654", "is_blocked": false}, "192.168.1.30": {"in_traffic": 422, "out_traffic": 251, "threats": 0, "last_seen": "2026-05-23T10:10:49.190292", "is_blocked": false}, "192.168.1.90": {"in_traffic": 508, "out_traffic": 163, "threats": 0, "last_seen": "2026-05-23T10:09:19.588996", "is_blocked": false}, "192.168.1.46": {"in_traffic": 433, "out_traffic": 203, "threats": 0, "last_seen": "2026-05-23T10:10:25.087544", "is_blocked": false}, "192.168.1.197": {"in_traffic": 753, "out_traffic": 294, "threats": 0, "last_seen": "2026-05-23T10:09:43.798863", "is_blocked": false}, "192.168.1.220": {"in_traffic": 182, "out_traffic": 120, "threats": 0, "last_seen": "2026-05-23T10:09:45.870335", "is_blocked": false}, "192.168.1.7": {"in_traffic": 521, "out_traffic": 229, "threats": 0, "last_seen": "2026-05-23T10:11:20.251665", "is_blocked": false}, "192.168.1.102": {"in_traffic": 173, "out_traffic": 131, "threats": 0, "last_seen": "2026-05-23T10:10:41.904833", "is_blocked": false}, "192.168.1.181": {"in_traffic": 192, "out_traffic": 159, "threats": 0, "last_seen": "2026-05-23T10:10:12.629772", "is_blocked": false}, "192.168.1.132": {"in_traffic": 350, "out_traffic": 129, "threats": 1, "last_seen": "2026-05-23T10:10:39.796790", "is_blocked": false}, "192.168.1.104": {"in_traffic": 446, "out_traffic": 243, "threats": 0, "last_seen": "2026-05-23T10:10:57.516230", "is_blocked": false}, "192.168.1.247": {"in_traffic": 596, "out_traffic": 263, "threats": 0, "last_seen": "2026-05-23T10:11:21.285548", "is_blocked": false}, "192.168.1.18": {"in_traffic": 305, "out_traffic": 135, "threats": 0, "last_seen": "2026-05-23T10:11:16.108311", "is_blocked": false}, "192.168.1.245": {"in_traffic": 374, "out_traffic": 193, "threats": 1, "last_seen": "2026-05-23T10:11:03.722153", "is_blocked": false}, "192.168.1.127": {"in_traffic": 595, "out_traffic": 298, "threats": 1, "last_seen": "2026-05-23T10:11:09.892616", "is_blocked": false}, "192.168.1.44": {"in_traffic": 471, "out_traffic": 226, "threats": 0, "last_seen": "2026-05-23T10:10:32.412556", "is_blocked": false}, "192.168.1.12": {"in_traffic": 304, "out_traffic": 186, "threats": 1, "last_seen": "2026-05-23T10:11:03.722153", "is_blocked": false}, "192.168.1.119": {"in_traffic": 358, "out_traffic": 202, "threats": 0, "last_seen": "2026-05-23T10:09:57.217706", "is_blocked": false}, "192.168.1.13": {"in_traffic": 388, "out_traffic": 105, "threats": 0, "last_seen": "2026-05-23T10:07:08.922412", "is_blocked": false}, "192.168.1.94": {"in_traffic": 419, "out_traffic": 161, "threats": 1, "last_seen": "2026-05-23T10:11:07.827384", "is_blocked": false}, "192.168.1.248": {"in_traffic": 233, "out_traffic": 120, "threats": 0, "last_seen": "2026-05-23T10:11:00.607984", "is_blocked": false}, "192.168.1.93": {"in_traffic": 267, "out_traffic": 112, "threats": 0, "last_seen": "2026-05-23T10:10:53.404005", "is_blocked": false}, "192.168.1.186": {"in_traffic": 240, "out_traffic": 198, "threats": 1, "last_seen": "2026-05-23T10:11:21.285548", "is_blocked": false}, "192.168.1.192": {"in_traffic": 123, "out_traffic": 106, "threats": 0, "last_seen": "2026-05-23T10:07:23.565674", "is_blocked": false}, "192.168.1.234": {"in_traffic": 263, "out_traffic": 130, "threats": 1, "last_seen": "2026-05-23T10:11:17.149082", "is_blocked": false}, "192.168.1.232": {"in_traffic": 259, "out_traffic": 146, "threats": 0, "last_seen": "2026-05-23T10:09:16.362124", "is_blocked": false}, "192.168.1.162": {"in_traffic": 412, "out_traffic": 207, "threats": 1, "last_seen": "2026-05-23T10:10:45.034293", "is_blocked": false}, "192.168.1.5": {"in_traffic": 598, "out_traffic": 186, "threats": 0, "last_seen": "2026-05-23T10:11:04.755121", "is_blocked": false}, "192.168.1.139": {"in_traffic": 484, "out_traffic": 294, "threats": 0, "last_seen": "2026-05-23T10:11:08.854233", "is_blocked": false}, "192.168.1.211": {"in_traffic": 298, "out_traffic": 54, "threats": 1, "last_seen": "2026-05-23T10:10:30.335436", "is_blocked": false}, "192.168.1.137": {"in_traffic": 328, "out_traffic": 222, "threats": 0, "last_seen": "2026-05-23T10:10:19.833739", "is_blocked": false}, "192.168.1.112": {"in_traffic": 222, "out_traffic": 219, "threats": 0, "last_seen": "2026-05-23T10:11:21.285548", "is_blocked": false}, "192.168.1.251": {"in_traffic": 400, "out_traffic": 221, "threats": 0, "last_seen": "2026-05-23T10:09:28.029655", "is_blocked": false}, "192.168.1.219": {"in_traffic": 219, "out_traffic": 132, "threats": 0, "last_seen": "2026-05-23T10:10:36.636371", "is_blocked": false}, "192.168.1.184": {"in_traffic": 465, "out_traffic": 156, "threats": 0, "last_seen": "2026-05-23T10:11:02.689574", "is_blocked": false}, "192.168.1.182": {"in_traffic": 227, "out_traffic": 108, "threats": 1, "last_seen": "2026-05-23T10:10:49.190292", "is_blocked": false}, "192.168.1.14": {"in_traffic": 222, "out_traffic": 105, "threats": 1, "last_seen": "2026-05-23T10:09:55.150342", "is_blocked": false}, "192.168.1.57": {"in_traffic": 313, "out_traffic": 162, "threats": 1, "last_seen": "2026-05-23T10:11:16.108311", "is_blocked": false}, "192.168.1.67": {"in_traffic": 368, "out_traffic": 129, "threats": 1, "last_seen": "2026-05-23T10:11:15.077032", "is_blocked": false}, "192.168.1.140": {"in_traffic": 342, "out_traffic": 153, "threats": 0, "last_seen": "2026-05-23T10:10:25.087544", "is_blocked": false}, "192.168.1.37": {"in_traffic": 224, "out_traffic": 190, "threats": 1, "last_seen": "2026-05-23T10:10:28.220778", "is_blocked": false}, "192.168.1.47": {"in_traffic": 297, "out_traffic": 150, "threats": 0, "last_seen": "2026-05-23T10:10:55.464228", "is_blocked": false}, "192.168.1.191": {"in_traffic": 592, "out_traffic": 263, "threats": 1, "last_seen": "2026-05-23T10:10:10.581249", "is_blocked": false}, "192.168.1.2": {"in_traffic": 529, "out_traffic": 299, "threats": 0, "last_seen": "2026-05-23T10:11:03.722153", "is_blocked": false}, "192.168.1.142": {"in_traffic": 249, "out_traffic": 162, "threats": 1, "last_seen": "2026-05-23T10:11:01.657869", "is_blocked": false}, "192.168.1.136": {"in_traffic": 368, "out_traffic": 94, "threats": 1, "last_seen": "2026-05-23T10:10:52.380726", "is_blocked": false}, "192.168.1.128": {"in_traffic": 393, "out_traffic": 227, "threats": 0, "last_seen": "2026-05-23T10:10:45.034293", "is_blocked": false}, "192.168.1.179": {"in_traffic": 451, "out_traffic": 151, "threats": 0, "last_seen": "2026-05-23T10:10:35.588510", "is_blocked": false}, "192.168.1.190": {"in_traffic": 258, "out_traffic": 108, "threats": 0, "last_seen": "2026-05-23T10:10:32.412556", "is_blocked": false}, "192.168.1.103": {"in_traffic": 339, "out_traffic": 163, "threats": 1, "last_seen": "2026-05-23T10:11:11.958547", "is_blocked": false}, "192.168.1.235": {"in_traffic": 185, "out_traffic": 79, "threats": 0, "last_seen": "2026-05-23T10:11:14.051858", "is_blocked": false}, "192.168.1.89": {"in_traffic": 391, "out_traffic": 123, "threats": 0, "last_seen": "2026-05-23T10:10:34.533022", "is_blocked": false}, "192.168.1.120": {"in_traffic": 270, "out_traffic": 109, "threats": 0, "last_seen": "2026-05-23T10:10:52.380726", "is_blocked": false}, "192.168.1.246": {"in_traffic": 283, "out_traffic": 95, "threats": 0, "last_seen": "2026-05-23T10:10:55.464228", "is_blocked": false}, "192.168.1.163": {"in_traffic": 388, "out_traffic": 203, "threats": 0, "last_seen": "2026-05-23T10:10:51.309193", "is_blocked": false}, "192.168.1.242": {"in_traffic": 232, "out_traffic": 135, "threats": 1, "last_seen": "2026-05-23T10:11:00.607984", "is_blocked": false}, "192.168.1.52": {"in_traffic": 287, "out_traffic": 83, "threats": 1, "last_seen": "2026-05-23T10:11:12.988582", "is_blocked": false}, "192.168.1.229": {"in_traffic": 635, "out_traffic": 286, "threats": 2, "last_seen": "2026-05-23T10:10:53.404005", "is_blocked": false}, "192.168.1.218": {"in_traffic": 311, "out_traffic": 122, "threats": 0, "last_seen": "2026-05-23T10:10:19.833739", "is_blocked": false}, "192.168.1.180": {"in_traffic": 286, "out_traffic": 231, "threats": 0, "last_seen": "2026-05-23T10:11:10.924548", "is_blocked": false}, "192.168.1.70": {"in_traffic": 264, "out_traffic": 119, "threats": 0, "last_seen": "2026-05-23T10:11:06.800047", "is_blocked": false}, "192.168.1.113": {"in_traffic": 387, "out_traffic": 267, "threats": 0, "last_seen": "2026-05-23T10:09:58.250024", "is_blocked": false}, "192.168.1.237": {"in_traffic": 316, "out_traffic": 194, "threats": 0, "last_seen": "2026-05-23T10:10:49.190292", "is_blocked": false}, "192.168.1.124": {"in_traffic": 125, "out_traffic": 132, "threats": 1, "last_seen": "2026-05-23T10:10:21.943352", "is_blocked": false}, "192.168.1.42": {"in_traffic": 266, "out_traffic": 119, "threats": 1, "last_seen": "2026-05-23T10:10:56.486423", "is_blocked": false}, "192.168.1.76": {"in_traffic": 378, "out_traffic": 230, "threats": 1, "last_seen": "2026-05-23T10:11:11.958547", "is_blocked": false}, "192.168.1.19": {"in_traffic": 428, "out_traffic": 236, "threats": 1, "last_seen": "2026-05-23T10:11:02.689574", "is_blocked": false}, "192.168.1.45": {"in_traffic": 238, "out_traffic": 115, "threats": 1, "last_seen": "2026-05-23T10:11:05.776655", "is_blocked": false}, "192.168.1.22": {"in_traffic": 520, "out_traffic": 194, "threats": 0, "last_seen": "2026-05-23T10:10:57.516230", "is_blocked": false}, "192.168.1.231": {"in_traffic": 164, "out_traffic": 202, "threats": 1, "last_seen": "2026-05-23T10:11:06.800047", "is_blocked": false}, "192.168.1.129": {"in_traffic": 399, "out_traffic": 122, "threats": 2, "last_seen": "2026-05-23T10:10:56.486423", "is_blocked": false}, "192.168.1.53": {"in_traffic": 556, "out_traffic": 275, "threats": 0, "last_seen": "2026-05-23T10:09:17.482532", "is_blocked": false}, "192.168.1.91": {"in_traffic": 451, "out_traffic": 172, "threats": 0, "last_seen": "2026-05-23T10:10:26.132375", "is_blocked": false}, "192.168.1.138": {"in_traffic": 450, "out_traffic": 212, "threats": 0, "last_seen": "2026-05-23T10:10:57.516230", "is_blocked": false}, "192.168.1.49": {"in_traffic": 295, "out_traffic": 205, "threats": 0, "last_seen": "2026-05-23T10:10:37.701349", "is_blocked": false}, "192.168.1.59": {"in_traffic": 311, "out_traffic": 139, "threats": 0, "last_seen": "2026-05-23T10:11:12.988582", "is_blocked": false}, "192.168.1.108": {"in_traffic": 395, "out_traffic": 314, "threats": 0, "last_seen": "2026-05-23T10:10:21.943352", "is_blocked": false}, "192.168.1.185": {"in_traffic": 351, "out_traffic": 114, "threats": 0, "last_seen": "2026-05-23T10:11:08.854233", "is_blocked": false}, "192.168.1.147": {"in_traffic": 234, "out_traffic": 173, "threats": 0, "last_seen": "2026-05-23T10:11:12.988582", "is_blocked": false}, "192.168.1.215": {"in_traffic": 337, "out_traffic": 159, "threats": 0, "last_seen": "2026-05-23T10:09:52.039364", "is_blocked": false}, "192.168.1.196": {"in_traffic": 346, "out_traffic": 208, "threats": 0, "last_seen": "2026-05-23T10:10:32.412556", "is_blocked": false}, "192.168.1.126": {"in_traffic": 265, "out_traffic": 162, "threats": 0, "last_seen": "2026-05-23T10:11:08.854233", "is_blocked": false}, "192.168.1.149": {"in_traffic": 272, "out_traffic": 205, "threats": 1, "last_seen": "2026-05-23T10:11:00.607984", "is_blocked": false}, "192.168.1.74": {"in_traffic": 291, "out_traffic": 172, "threats": 1, "last_seen": "2026-05-23T10:11:09.892616", "is_blocked": false}, "192.168.1.72": {"in_traffic": 238, "out_traffic": 142, "threats": 2, "last_seen": "2026-05-23T10:10:50.246298", "is_blocked": false}, "192.168.1.189": {"in_traffic": 318, "out_traffic": 175, "threats": 1, "last_seen": "2026-05-23T10:10:07.504141", "is_blocked": false}, "192.168.1.145": {"in_traffic": 78, "out_traffic": 49, "threats": 0, "last_seen": "2026-05-23T10:10:34.533022", "is_blocked": false}, "192.168.1.227": {"in_traffic": 172, "out_traffic": 127, "threats": 0, "last_seen": "2026-05-23T10:11:20.251665", "is_blocked": false}, "192.168.1.165": {"in_traffic": 264, "out_traffic": 74, "threats": 0, "last_seen": "2026-05-23T10:10:30.335436", "is_blocked": false}, "192.168.1.188": {"in_traffic": 286, "out_traffic": 193, "threats": 1, "last_seen": "2026-05-23T10:10:08.528063", "is_blocked": false}, "192.168.1.249": {"in_traffic": 249, "out_traffic": 159, "threats": 1, "last_seen": "2026-05-23T10:10:37.701349", "is_blocked": false}, "192.168.1.172": {"in_traffic": 267, "out_traffic": 150, "threats": 0, "last_seen": "2026-05-23T10:11:16.108311", "is_blocked": false}, "192.168.1.225": {"in_traffic": 367, "out_traffic": 170, "threats": 0, "last_seen": "2026-05-23T10:10:38.752475", "is_blocked": false}, "192.168.1.58": {"in_traffic": 486, "out_traffic": 244, "threats": 2, "last_seen": "2026-05-23T10:11:17.149082", "is_blocked": false}, "192.168.1.84": {"in_traffic": 500, "out_traffic": 284, "threats": 0, "last_seen": "2026-05-23T10:11:19.227174", "is_blocked": false}, "192.168.1.110": {"in_traffic": 464, "out_traffic": 261, "threats": 0, "last_seen": "2026-05-23T10:11:10.924548", "is_blocked": false}, "192.168.1.40": {"in_traffic": 381, "out_traffic": 202, "threats": 0, "last_seen": "2026-05-23T10:11:06.800047", "is_blocked": false}, "192.168.1.164": {"in_traffic": 295, "out_traffic": 128, "threats": 0, "last_seen": "2026-05-23T10:10:27.171358", "is_blocked": false}, "192.168.1.244": {"in_traffic": 313, "out_traffic": 237, "threats": 0, "last_seen": "2026-05-23T10:11:05.776655", "is_blocked": false}, "192.168.1.155": {"in_traffic": 187, "out_traffic": 85, "threats": 0, "last_seen": "2026-05-23T10:10:45.034293", "is_blocked": false}, "192.168.1.34": {"in_traffic": 554, "out_traffic": 204, "threats": 0, "last_seen": "2026-05-23T10:11:17.149082", "is_blocked": false}, "192.168.1.125": {"in_traffic": 604, "out_traffic": 204, "threats": 1, "last_seen": "2026-05-23T10:10:52.380726", "is_blocked": false}, "192.168.1.254": {"in_traffic": 129, "out_traffic": 85, "threats": 1, "last_seen": "2026-05-23T10:08:27.448195", "is_blocked": false}, "192.168.1.8": {"in_traffic": 715, "out_traffic": 408, "threats": 0, "last_seen": "2026-05-23T10:11:19.227174", "is_blocked": false}, "192.168.1.209": {"in_traffic": 667, "out_traffic": 261, "threats": 1, "last_seen": "2026-05-23T10:11:03.722153", "is_blocked": false}, "192.168.1.39": {"in_traffic": 323, "out_traffic": 125, "threats": 0, "last_seen": "2026-05-23T10:10:18.781983", "is_blocked": false}, "192.168.1.148": {"in_traffic": 485, "out_traffic": 262, "threats": 1, "last_seen": "2026-05-23T10:08:29.512818", "is_blocked": false}, "192.168.1.99": {"in_traffic": 542, "out_traffic": 152, "threats": 0, "last_seen": "2026-05-23T10:11:18.185931", "is_blocked": false}, "192.168.1.71": {"in_traffic": 381, "out_traffic": 102, "threats": 1, "last_seen": "2026-05-23T10:10:47.090813", "is_blocked": false}, "192.168.1.15": {"in_traffic": 235, "out_traffic": 85, "threats": 1, "last_seen": "2026-05-23T10:09:01.804352", "is_blocked": false}, "192.168.1.56": {"in_traffic": 356, "out_traffic": 136, "threats": 0, "last_seen": "2026-05-23T10:09:51.009352", "is_blocked": false}, "192.168.1.117": {"in_traffic": 414, "out_traffic": 159, "threats": 1, "last_seen": "2026-05-23T10:10:40.847436", "is_blocked": false}, "192.168.1.233": {"in_traffic": 188, "out_traffic": 151, "threats": 0, "last_seen": "2026-05-23T10:10:57.516230", "is_blocked": false}, "192.168.1.210": {"in_traffic": 578, "out_traffic": 248, "threats": 0, "last_seen": "2026-05-23T10:10:59.572887", "is_blocked": false}, "192.168.1.61": {"in_traffic": 211, "out_traffic": 97, "threats": 2, "last_seen": "2026-05-23T10:11:11.958547", "is_blocked": false}, "192.168.1.133": {"in_traffic": 136, "out_traffic": 22, "threats": 0, "last_seen": "2026-05-23T10:10:38.752475", "is_blocked": false}, "192.168.1.154": {"in_traffic": 335, "out_traffic": 184, "threats": 0, "last_seen": "2026-05-23T10:11:07.827384", "is_blocked": false}, "192.168.1.222": {"in_traffic": 301, "out_traffic": 203, "threats": 2, "last_seen": "2026-05-23T10:10:51.309193", "is_blocked": false}, "192.168.1.83": {"in_traffic": 274, "out_traffic": 138, "threats": 0, "last_seen": "2026-05-23T10:10:52.380726", "is_blocked": false}, "192.168.1.55": {"in_traffic": 307, "out_traffic": 161, "threats": 0, "last_seen": "2026-05-23T10:11:08.854233", "is_blocked": false}, "192.168.1.63": {"in_traffic": 254, "out_traffic": 243, "threats": 1, "last_seen": "2026-05-23T10:09:46.892875", "is_blocked": false}, "192.168.1.202": {"in_traffic": 211, "out_traffic": 78, "threats": 0, "last_seen": "2026-05-23T10:09:54.122642", "is_blocked": false}, "192.168.1.141": {"in_traffic": 295, "out_traffic": 180, "threats": 1, "last_seen": "2026-05-23T10:10:50.246298", "is_blocked": false}, "192.168.1.100": {"in_traffic": 195, "out_traffic": 147, "threats": 1, "last_seen": "2026-05-23T10:11:18.185931", "is_blocked": false}, "192.168.1.167": {"in_traffic": 352, "out_traffic": 141, "threats": 0, "last_seen": "2026-05-23T10:11:08.854233", "is_blocked": false}, "192.168.1.50": {"in_traffic": 195, "out_traffic": 142, "threats": 0, "last_seen": "2026-05-23T10:10:26.132375", "is_blocked": false}, "192.168.1.4": {"in_traffic": 357, "out_traffic": 177, "threats": 0, "last_seen": "2026-05-23T10:10:42.964257", "is_blocked": false}, "192.168.1.123": {"in_traffic": 316, "out_traffic": 241, "threats": 0, "last_seen": "2026-05-23T10:11:19.227174", "is_blocked": false}, "192.168.1.212": {"in_traffic": 339, "out_traffic": 259, "threats": 1, "last_seen": "2026-05-23T10:10:55.464228", "is_blocked": false}, "192.168.1.82": {"in_traffic": 259, "out_traffic": 95, "threats": 1, "last_seen": "2026-05-23T10:10:33.490979", "is_blocked": false}, "192.168.1.201": {"in_traffic": 333, "out_traffic": 160, "threats": 0, "last_seen": "2026-05-23T10:10:30.335436", "is_blocked": false}, "192.168.1.216": {"in_traffic": 422, "out_traffic": 251, "threats": 1, "last_seen": "2026-05-23T10:09:44.841520", "is_blocked": false}, "192.168.1.252": {"in_traffic": 511, "out_traffic": 176, "threats": 0, "last_seen": "2026-05-23T10:10:47.090813", "is_blocked": false}, "192.168.1.243": {"in_traffic": 303, "out_traffic": 108, "threats": 0, "last_seen": "2026-05-23T10:09:19.588996", "is_blocked": false}, "192.168.1.11": {"in_traffic": 362, "out_traffic": 194, "threats": 1, "last_seen": "2026-05-23T10:10:53.404005", "is_blocked": false}, "192.168.1.170": {"in_traffic": 83, "out_traffic": 38, "threats": 0, "last_seen": "2026-05-23T10:07:12.192141", "is_blocked": false}, "192.168.1.187": {"in_traffic": 367, "out_traffic": 214, "threats": 0, "last_seen": "2026-05-23T10:11:14.051858", "is_blocked": false}, "192.168.1.23": {"in_traffic": 341, "out_traffic": 172, "threats": 0, "last_seen": "2026-05-23T10:10:59.572887", "is_blocked": false}, "192.168.1.238": {"in_traffic": 163, "out_traffic": 126, "threats": 0, "last_seen": "2026-05-23T10:11:18.185931", "is_blocked": false}, "192.168.1.96": {"in_traffic": 189, "out_traffic": 77, "threats": 1, "last_seen": "2026-05-23T10:11:05.776655", "is_blocked": false}, "192.168.1.223": {"in_traffic": 502, "out_traffic": 205, "threats": 1, "last_seen": "2026-05-23T10:11:17.149082", "is_blocked": false}, "192.168.1.174": {"in_traffic": 307, "out_traffic": 104, "threats": 0, "last_seen": "2026-05-23T10:11:15.077032", "is_blocked": false}, "192.168.1.151": {"in_traffic": 351, "out_traffic": 238, "threats": 0, "last_seen": "2026-05-23T10:10:50.246298", "is_blocked": false}, "192.168.1.51": {"in_traffic": 465, "out_traffic": 348, "threats": 1, "last_seen": "2026-05-23T10:10:49.190292", "is_blocked": false}, "192.168.1.98": {"in_traffic": 340, "out_traffic": 188, "threats": 0, "last_seen": "2026-05-23T10:09:39.677610", "is_blocked": false}, "192.168.1.81": {"in_traffic": 338, "out_traffic": 181, "threats": 0, "last_seen": "2026-05-23T10:11:10.924548", "is_blocked": false}, "192.168.1.175": {"in_traffic": 18, "out_traffic": 63, "threats": 0, "last_seen": "2026-05-23T10:08:29.512818", "is_blocked": false}, "192.168.1.109": {"in_traffic": 395, "out_traffic": 86, "threats": 0, "last_seen": "2026-05-23T10:10:14.677310", "is_blocked": false}, "192.168.1.130": {"in_traffic": 324, "out_traffic": 251, "threats": 1, "last_seen": "2026-05-23T10:10:59.572887", "is_blocked": false}, "192.168.1.150": {"in_traffic": 241, "out_traffic": 82, "threats": 1, "last_seen": "2026-05-23T10:11:11.958547", "is_blocked": false}, "192.168.1.107": {"in_traffic": 318, "out_traffic": 181, "threats": 0, "last_seen": "2026-05-23T10:11:20.251665", "is_blocked": false}, "192.168.1.134": {"in_traffic": 60, "out_traffic": 71, "threats": 1, "last_seen": "2026-05-23T10:10:46.064803", "is_blocked": false}, "192.168.1.236": {"in_traffic": 126, "out_traffic": 71, "threats": 0, "last_seen": "2026-05-23T10:09:32.352551", "is_blocked": false}, "192.168.1.54": {"in_traffic": 240, "out_traffic": 84, "threats": 0, "last_seen": "2026-05-23T10:10:21.943352", "is_blocked": false}, "192.168.1.153": {"in_traffic": 253, "out_traffic": 70, "threats": 0, "last_seen": "2026-05-23T10:10:15.704265", "is_blocked": false}, "192.168.1.169": {"in_traffic": 347, "out_traffic": 119, "threats": 0, "last_seen": "2026-05-23T10:10:06.483660", "is_blocked": false}, "192.168.1.240": {"in_traffic": 191, "out_traffic": 145, "threats": 1, "last_seen": "2026-05-23T10:09:58.250024", "is_blocked": false}, "192.168.1.195": {"in_traffic": 419, "out_traffic": 242, "threats": 0, "last_seen": "2026-05-23T10:10:45.034293", "is_blocked": false}, "192.168.1.168": {"in_traffic": 527, "out_traffic": 258, "threats": 0, "last_seen": "2026-05-23T10:11:07.827384", "is_blocked": false}, "192.168.1.101": {"in_traffic": 309, "out_traffic": 133, "threats": 2, "last_seen": "2026-05-23T10:11:19.227174", "is_blocked": false}, "192.168.1.9": {"in_traffic": 100, "out_traffic": 101, "threats": 1, "last_seen": "2026-05-23T10:10:58.548241", "is_blocked": false}, "192.168.1.73": {"in_traffic": 488, "out_traffic": 199, "threats": 0, "last_seen": "2026-05-23T10:10:47.090813", "is_blocked": false}, "192.168.1.116": {"in_traffic": 333, "out_traffic": 165, "threats": 0, "last_seen": "2026-05-23T10:11:06.800047", "is_blocked": false}, "192.168.1.79": {"in_traffic": 356, "out_traffic": 193, "threats": 0, "last_seen": "2026-05-23T10:10:27.171358", "is_blocked": false}, "192.168.1.152": {"in_traffic": 207, "out_traffic": 92, "threats": 0, "last_seen": "2026-05-23T10:10:09.551026", "is_blocked": false}, "192.168.1.226": {"in_traffic": 488, "out_traffic": 94, "threats": 0, "last_seen": "2026-05-23T10:09:14.263561", "is_blocked": false}, "192.168.1.33": {"in_traffic": 125, "out_traffic": 90, "threats": 0, "last_seen": "2026-05-23T10:09:25.907445", "is_blocked": false}, "192.168.1.206": {"in_traffic": 152, "out_traffic": 56, "threats": 0, "last_seen": "2026-05-23T10:09:52.039364", "is_blocked": false}, "192.168.1.62": {"in_traffic": 166, "out_traffic": 118, "threats": 1, "last_seen": "2026-05-23T10:11:19.227174", "is_blocked": false}, "192.168.1.66": {"in_traffic": 257, "out_traffic": 176, "threats": 0, "last_seen": "2026-05-23T10:11:20.251665", "is_blocked": false}, "192.168.1.111": {"in_traffic": 454, "out_traffic": 204, "threats": 0, "last_seen": "2026-05-23T10:10:56.486423", "is_blocked": false}, "192.168.1.131": {"in_traffic": 837, "out_traffic": 243, "threats": 0, "last_seen": "2026-05-23T10:10:54.426398", "is_blocked": false}, "192.168.1.239": {"in_traffic": 379, "out_traffic": 172, "threats": 0, "last_seen": "2026-05-23T10:09:48.953276", "is_blocked": false}, "192.168.1.26": {"in_traffic": 205, "out_traffic": 195, "threats": 0, "last_seen": "2026-05-23T10:11:09.892616", "is_blocked": false}, "192.168.1.92": {"in_traffic": 150, "out_traffic": 107, "threats": 0, "last_seen": "2026-05-23T10:10:36.636371", "is_blocked": false}, "192.168.1.17": {"in_traffic": 322, "out_traffic": 188, "threats": 0, "last_seen": "2026-05-23T10:10:52.380726", "is_blocked": false}, "192.168.1.205": {"in_traffic": 253, "out_traffic": 154, "threats": 1, "last_seen": "2026-05-23T10:10:20.901008", "is_blocked": false}, "192.168.1.146": {"in_traffic": 285, "out_traffic": 159, "threats": 0, "last_seen": "2026-05-23T10:09:54.122642", "is_blocked": false}, "192.168.1.217": {"in_traffic": 319, "out_traffic": 180, "threats": 0, "last_seen": "2026-05-23T10:10:15.704265", "is_blocked": false}, "192.168.1.183": {"in_traffic": 502, "out_traffic": 157, "threats": 0, "last_seen": "2026-05-23T10:11:16.108311", "is_blocked": false}, "192.168.1.86": {"in_traffic": 325, "out_traffic": 157, "threats": 0, "last_seen": "2026-05-23T10:10:51.309193", "is_blocked": false}, "192.168.1.224": {"in_traffic": 273, "out_traffic": 95, "threats": 0, "last_seen": "2026-05-23T10:11:01.657869", "is_blocked": false}, "192.168.1.114": {"in_traffic": 418, "out_traffic": 186, "threats": 0, "last_seen": "2026-05-23T10:10:42.964257", "is_blocked": false}, "192.168.1.78": {"in_traffic": 482, "out_traffic": 105, "threats": 0, "last_seen": "2026-05-23T10:11:14.051858", "is_blocked": false}, "192.168.1.29": {"in_traffic": 281, "out_traffic": 125, "threats": 0, "last_seen": "2026-05-23T10:10:14.677310", "is_blocked": false}, "192.168.1.64": {"in_traffic": 140, "out_traffic": 95, "threats": 0, "last_seen": "2026-05-23T10:10:08.528063", "is_blocked": false}, "192.168.1.21": {"in_traffic": 345, "out_traffic": 128, "threats": 0, "last_seen": "2026-05-23T10:09:49.980718", "is_blocked": false}, "192.168.1.28": {"in_traffic": 240, "out_traffic": 89, "threats": 0, "last_seen": "2026-05-23T10:08:46.173285", "is_blocked": false}, "192.168.1.166": {"in_traffic": 211, "out_traffic": 137, "threats": 0, "last_seen": "2026-05-23T10:11:04.755121", "is_blocked": false}, "192.168.1.65": {"in_traffic": 432, "out_traffic": 169, "threats": 0, "last_seen": "2026-05-23T10:10:18.781983", "is_blocked": false}, "192.168.1.178": {"in_traffic": 340, "out_traffic": 172, "threats": 0, "last_seen": "2026-05-23T10:09:48.953276", "is_blocked": false}, "192.168.1.20": {"in_traffic": 10, "out_traffic": 15, "threats": 1, "last_seen": "2026-05-23T10:08:50.389082", "is_blocked": false}, "192.168.1.121": {"in_traffic": 273, "out_traffic": 74, "threats": 0, "last_seen": "2026-05-23T10:10:09.551026", "is_blocked": false}, "192.168.1.3": {"in_traffic": 326, "out_traffic": 154, "threats": 1, "last_seen": "2026-05-23T10:11:01.657869", "is_blocked": false}, "192.168.1.85": {"in_traffic": 324, "out_traffic": 170, "threats": 0, "last_seen": "2026-05-23T10:11:02.689574", "is_blocked": false}, "192.168.1.214": {"in_traffic": 280, "out_traffic": 157, "threats": 0, "last_seen": "2026-05-23T10:10:57.516230", "is_blocked": false}, "192.168.1.200": {"in_traffic": 154, "out_traffic": 67, "threats": 2, "last_seen": "2026-05-23T10:11:18.185931", "is_blocked": false}, "192.168.1.177": {"in_traffic": 390, "out_traffic": 171, "threats": 2, "last_seen": "2026-05-23T10:11:11.958547", "is_blocked": false}, "192.168.1.95": {"in_traffic": 403, "out_traffic": 226, "threats": 0, "last_seen": "2026-05-23T10:11:19.227174", "is_blocked": false}, "192.168.1.221": {"in_traffic": 113, "out_traffic": 107, "threats": 0, "last_seen": "2026-05-23T10:10:48.136898", "is_blocked": false}, "192.168.1.203": {"in_traffic": 361, "out_traffic": 203, "threats": 1, "last_seen": "2026-05-23T10:10:46.064803", "is_blocked": false}, "192.168.1.122": {"in_traffic": 379, "out_traffic": 139, "threats": 0, "last_seen": "2026-05-23T10:11:14.051858", "is_blocked": false}, "192.168.1.35": {"in_traffic": 250, "out_traffic": 132, "threats": 0, "last_seen": "2026-05-23T10:11:15.077032", "is_blocked": false}, "192.168.1.204": {"in_traffic": 144, "out_traffic": 82, "threats": 0, "last_seen": "2026-05-23T10:11:04.755121", "is_blocked": false}, "192.168.1.43": {"in_traffic": 214, "out_traffic": 66, "threats": 0, "last_seen": "2026-05-23T10:09:41.744739", "is_blocked": false}, "192.168.1.135": {"in_traffic": 224, "out_traffic": 94, "threats": 0, "last_seen": "2026-05-23T10:10:16.737430", "is_blocked": false}, "192.168.1.171": {"in_traffic": 98, "out_traffic": 59, "threats": 0, "last_seen": "2026-05-23T10:09:29.097628", "is_blocked": false}, "192.168.1.207": {"in_traffic": 173, "out_traffic": 87, "threats": 0, "last_seen": "2026-05-23T10:10:24.021641", "is_blocked": false}, "192.168.1.160": {"in_traffic": 138, "out_traffic": 45, "threats": 0, "last_seen": "2026-05-23T10:11:15.077032", "is_blocked": false}, "192.168.1.157": {"in_traffic": 249, "out_traffic": 215, "threats": 0, "last_seen": "2026-05-23T10:10:48.136898", "is_blocked": false}, "192.168.1.80": {"in_traffic": 141, "out_traffic": 80, "threats": 0, "last_seen": "2026-05-23T10:10:58.548241", "is_blocked": false}, "192.168.1.230": {"in_traffic": 62, "out_traffic": 111, "threats": 0, "last_seen": "2026-05-23T10:10:18.781983", "is_blocked": false}, "192.168.1.198": {"in_traffic": 228, "out_traffic": 162, "threats": 1, "last_seen": "2026-05-23T10:10:54.426398", "is_blocked": false}, "192.168.1.176": {"in_traffic": 123, "out_traffic": 107, "threats": 0, "last_seen": "2026-05-23T10:10:43.999991", "is_blocked": false}, "192.168.1.241": {"in_traffic": 279, "out_traffic": 111, "threats": 0, "last_seen": "2026-05-23T10:09:18.545329", "is_blocked": false}, "192.168.1.156": {"in_traffic": 296, "out_traffic": 108, "threats": 1, "last_seen": "2026-05-23T10:11:16.108311", "is_blocked": false}, "192.168.1.48": {"in_traffic": 141, "out_traffic": 112, "threats": 1, "last_seen": "2026-05-23T10:10:30.335436", "is_blocked": false}, "192.168.1.97": {"in_traffic": 294, "out_traffic": 117, "threats": 0, "last_seen": "2026-05-23T10:11:14.051858", "is_blocked": false}, "192.168.1.60": {"in_traffic": 570, "out_traffic": 235, "threats": 0, "last_seen": "2026-05-23T10:10:50.246298", "is_blocked": false}, "192.168.1.69": {"in_traffic": 253, "out_traffic": 152, "threats": 0, "last_seen": "2026-05-23T10:11:03.722153", "is_blocked": false}, "192.168.1.41": {"in_traffic": 118, "out_traffic": 23, "threats": 0, "last_seen": "2026-05-23T10:10:14.677310", "is_blocked": false}, "192.168.1.199": {"in_traffic": 22, "out_traffic": 13, "threats": 0, "last_seen": "2026-05-23T10:08:34.683693", "is_blocked": false}, "192.168.1.213": {"in_traffic": 31, "out_traffic": 19, "threats": 1, "last_seen": "2026-05-23T10:09:17.482532", "is_blocked": false}, "192.168.1.253": {"in_traffic": 149, "out_traffic": 157, "threats": 0, "last_seen": "2026-05-23T10:10:39.796790", "is_blocked": false}, "192.168.1.25": {"in_traffic": 403, "out_traffic": 191, "threats": 0, "last_seen": "2026-05-23T10:10:20.901008", "is_blocked": false}, "192.168.1.24": {"in_traffic": 80, "out_traffic": 27, "threats": 0, "last_seen": "2026-05-23T10:08:48.263833", "is_blocked": false}, "192.168.1.194": {"in_traffic": 236, "out_traffic": 125, "threats": 0, "last_seen": "2026-05-23T10:09:59.276708", "is_blocked": false}, "192.168.1.77": {"in_traffic": 192, "out_traffic": 131, "threats": 0, "last_seen": "2026-05-23T10:11:18.185931", "is_blocked": false}, "192.168.1.6": {"in_traffic": 353, "out_traffic": 99, "threats": 0, "last_seen": "2026-05-23T10:10:30.335436", "is_blocked": false}, "192.168.1.106": {"in_traffic": 33, "out_traffic": 49, "threats": 0, "last_seen": "2026-05-23T10:11:09.892616", "is_blocked": false}, "192.168.1.75": {"in_traffic": 146, "out_traffic": 158, "threats": 0, "last_seen": "2026-05-23T10:10:39.796790", "is_blocked": false}, "192.168.1.10": {"in_traffic": 220, "out_traffic": 97, "threats": 0, "last_seen": "2026-05-23T10:10:55.464228", "is_blocked": false}, "192.168.1.16": {"in_traffic": 89, "out_traffic": 45, "threats": 0, "last_seen": "2026-05-23T10:10:40.847436", "is_blocked": false}, "192.168.1.158": {"in_traffic": 109, "out_traffic": 47, "threats": 0, "last_seen": "2026-05-23T10:09:53.088731", "is_blocked": false}, "192.168.1.144": {"in_traffic": 188, "out_traffic": 76, "threats": 0, "last_seen": "2026-05-23T10:11:20.251665", "is_blocked": false}, "192.168.1.173": {"in_traffic": 55, "out_traffic": 52, "threats": 1, "last_seen": "2026-05-23T10:09:43.798863", "is_blocked": false}, "192.168.1.31": {"in_traffic": 49, "out_traffic": 91, "threats": 0, "last_seen": "2026-05-23T10:09:26.945433", "is_blocked": false}, "192.168.1.88": {"in_traffic": 98, "out_traffic": 49, "threats": 0, "last_seen": "2026-05-23T10:10:35.588510", "is_blocked": false}, "192.168.1.228": {"in_traffic": 43, "out_traffic": 23, "threats": 0, "last_seen": "2026-05-23T10:10:16.737430", "is_blocked": false}}}