{"timestamp": "2026-04-25T15:56:24.252635", "traffic_in": 984064, "traffic_out": 100352, "connections": 99, "packets_processed": 247, "threats_detected": 15, "ips_blocked": 0, "protocol_stats": {"TCP": 65, "UDP": 152, "HTTP": 160, "HTTPS": 67, "ICMP": 124, "DNS": 86, "Other": 98}, "attack_stats": {"SQL\u6ce8\u5165": 4, "XSS\u653b\u51fb": 2, "DDoS\u653b\u51fb": 3, "\u7aef\u53e3\u626b\u63cf": 2, "\u66b4\u529b\u7834\u89e3": 1, "\u5f02\u5e38\u6d41\u91cf": 1, "\u75c5\u6bd2/\u6728\u9a6c": 2}, "ip_data": {"192.168.1.22": {"in_traffic": 272, "out_traffic": 30, "threats": 0, "last_seen": "2026-04-25T15:56:21.880689", "is_blocked": false}, "192.168.1.73": {"in_traffic": 191, "out_traffic": 91, "threats": 0, "last_seen": "2026-04-25T15:56:18.392459", "is_blocked": false}, "192.168.1.38": {"in_traffic": 190, "out_traffic": 90, "threats": 0, "last_seen": "2026-04-25T15:56:19.548841", "is_blocked": false}, "192.168.1.128": {"in_traffic": 188, "out_traffic": 90, "threats": 0, "last_seen": "2026-04-25T15:56:18.392459", "is_blocked": false}, "192.168.1.43": {"in_traffic": 160, "out_traffic": 87, "threats": 0, "last_seen": "2026-04-25T15:55:59.219543", "is_blocked": false}}}